[{"type": "Feature", "geometry": {"type": "Point", "coordinates": [-74.1159074, 4.6310851]}, "properties": {"timestamp": 1559072215.0, "p25": 26}}, {"type": "Feature", "geometry": {"type": "Point", "coordinates": [-74.115904, 4.6310836]}, "properties": {"timestamp": 1559072220.0, "p25": 26}}, {"type": "Feature", "geometry": {"type": "Point", "coordinates": [-74.1158996, 4.6310816]}, "properties": {"timestamp": 1559072226.0, "p25": 24}}, {"type": "Feature", "geometry": {"type": "Point", "coordinates": [-74.1158994, 4.631081]}, "properties": {"timestamp": 1559072231.0, "p25": 22}}, {"type": "Feature", "geometry": {"type": "Point", "coordinates": [-74.1158978, 4.6310738]}, "properties": {"timestamp": 1559072236.0, "p25": 21}}, {"type": "Feature", "geometry": {"type": "Point", "coordinates": [-74.1158949, 4.6310662]}, "properties": {"timestamp": 1559072241.0, "p25": 21}}, {"type": "Feature", "geometry": {"type": "Point", "coordinates": [-74.1158943, 4.6310636]}, "properties": {"timestamp": 1559072246.0, "p25": 21}}, {"type": "Feature", "geometry": {"type": "Point", "coordinates": [-74.1158926, 4.631064]}, "properties": {"timestamp": 1559072251.0, "p25": 20}}, {"type": "Feature", "geometry": {"type": "Point", "coordinates": [-74.1158888, 4.6310656]}, "properties": {"timestamp": 1559072256.0, "p25": 19}}, {"type": "Feature", "geometry": {"type": "Point", "coordinates": [-74.1158872, 4.6310673]}, "properties": {"timestamp": 1559072261.0, "p25": 19}}, {"type": "Feature", "geometry": {"type": "Point", "coordinates": [-74.115886, 4.6310738]}, "properties": {"timestamp": 1559072267.0, "p25": 21}}, {"type": "Feature", "geometry": {"type": "Point", "coordinates": [-74.1158839, 4.6310788]}, "properties": {"timestamp": 1559072272.0, "p25": 22}}, {"type": "Feature", "geometry": {"type": "Point", "coordinates": [-74.1158794, 4.631069]}, "properties": {"timestamp": 1559072277.0, "p25": 20}}, {"type": "Feature", "geometry": {"type": "Point", "coordinates": [-74.1158714, 4.6310665]}, "properties": {"timestamp": 1559072282.0, "p25": 18}}, {"type": "Feature", "geometry": {"type": "Point", "coordinates": [-74.1158961, 4.631123]}, "properties": {"timestamp": 1559073187.0, "p25": 28}}, {"type": "Feature", "geometry": {"type": "Point", "coordinates": [-74.1159079, 4.631035]}, "properties": {"timestamp": 1559072527.0, "p25": 8}}, {"type": "Feature", "geometry": {"type": "Point", "coordinates": [-74.1159094, 4.6310353]}, "properties": {"timestamp": 1559072537.0, "p25": 9}}, {"type": "Feature", "geometry": {"type": "Point", "coordinates": [-74.115918, 4.6310434]}, "properties": {"timestamp": 1559072547.0, "p25": 12}}, {"type": "Feature", "geometry": {"type": "Point", "coordinates": [-74.1159202, 4.6310476]}, "properties": {"timestamp": 1559072557.0, "p25": 10}}, {"type": "Feature", "geometry": {"type": "Point", "coordinates": [-74.1159229, 4.6310541]}, "properties": {"timestamp": 1559072567.0, "p25": 11}}, {"type": "Feature", "geometry": {"type": "Point", "coordinates": [-74.1159234, 4.6310625]}, "properties": {"timestamp": 1559072578.0, "p25": 10}}, {"type": "Feature", "geometry": {"type": "Point", "coordinates": [-74.1159115, 4.6310507]}, "properties": {"timestamp": 1559072588.0, "p25": 10}}, {"type": "Feature", "geometry": {"type": "Point", "coordinates": [-74.1159108, 4.6310504]}, "properties": {"timestamp": 1559072598.0, "p25": 13}}, {"type": "Feature", "geometry": {"type": "Point", "coordinates": [-74.1159126, 4.6310505]}, "properties": {"timestamp": 1559072608.0, "p25": 15}}, {"type": "Feature", "geometry": {"type": "Point", "coordinates": [-74.1159141, 4.6310508]}, "properties": {"timestamp": 1559072618.0, "p25": 17}}, {"type": "Feature", "geometry": {"type": "Point", "coordinates": [-74.1158889, 4.6311143]}, "properties": {"timestamp": 1559073197.0, "p25": 26}}, {"type": "Feature", "geometry": {"type": "Point", "coordinates": [-74.1158886, 4.6311154]}, "properties": {"timestamp": 1559073207.0, "p25": 26}}, {"type": "Feature", "geometry": {"type": "Point", "coordinates": [-74.1158887, 4.6310974]}, "properties": {"timestamp": 1559073218.0, "p25": 26}}, {"type": "Feature", "geometry": {"type": "Point", "coordinates": [-74.1158936, 4.631075]}, "properties": {"timestamp": 1559073228.0, "p25": 28}}, {"type": "Feature", "geometry": {"type": "Point", "coordinates": [-74.115944, 4.6310693]}, "properties": {"timestamp": 1559073238.0, "p25": 19}}, {"type": "Feature", "geometry": {"type": "Point", "coordinates": [-74.1159182, 4.6310844]}, "properties": {"timestamp": 1559073248.0, "p25": 16}}, {"type": "Feature", "geometry": {"type": "Point", "coordinates": [-74.1159453, 4.6310806]}, "properties": {"timestamp": 1559073258.0, "p25": 16}}, {"type": "Feature", "geometry": {"type": "Point", "coordinates": [-74.1159483, 4.6310981]}, "properties": {"timestamp": 1559073268.0, "p25": 16}}, {"type": "Feature", "geometry": {"type": "Point", "coordinates": [-74.1159494, 4.6310971]}, "properties": {"timestamp": 1559073279.0, "p25": 15}}, {"type": "Feature", "geometry": {"type": "Point", "coordinates": [-74.1159402, 4.631115]}, "properties": {"timestamp": 1559073289.0, "p25": 14}}, {"type": "Feature", "geometry": {"type": "Point", "coordinates": [-74.1159466, 4.6310821]}, "properties": {"timestamp": 1559073299.0, "p25": 18}}, {"type": "Feature", "geometry": {"type": "Point", "coordinates": [-74.1159457, 4.631083]}, "properties": {"timestamp": 1559073309.0, "p25": 25}}, {"type": "Feature", "geometry": {"type": "Point", "coordinates": [-74.1159429, 4.6310853]}, "properties": {"timestamp": 1559073319.0, "p25": 25}}, {"type": "Feature", "geometry": {"type": "Point", "coordinates": [-74.1159293, 4.6311084]}, "properties": {"timestamp": 1559073329.0, "p25": 30}}, {"type": "Feature", "geometry": {"type": "Point", "coordinates": [-74.1158471, 4.6311218]}, "properties": {"timestamp": 1559073340.0, "p25": 30}}, {"type": "Feature", "geometry": {"type": "Point", "coordinates": [-74.1158451, 4.6311222]}, "properties": {"timestamp": 1559073350.0, "p25": 24}}, {"type": "Feature", "geometry": {"type": "Point", "coordinates": [-74.1158452, 4.6311221]}, "properties": {"timestamp": 1559073360.0, "p25": 20}}, {"type": "Feature", "geometry": {"type": "Point", "coordinates": [-74.1158481, 4.6311206]}, "properties": {"timestamp": 1559073370.0, "p25": 20}}, {"type": "Feature", "geometry": {"type": "Point", "coordinates": [-74.115861, 4.6311081]}, "properties": {"timestamp": 1559073380.0, "p25": 18}}, {"type": "Feature", "geometry": {"type": "Point", "coordinates": [-74.1158496, 4.6311152]}, "properties": {"timestamp": 1559073390.0, "p25": 16}}, {"type": "Feature", "geometry": {"type": "Point", "coordinates": [-74.1158837, 4.6311218]}, "properties": {"timestamp": 1559073400.0, "p25": 16}}, {"type": "Feature", "geometry": {"type": "Point", "coordinates": [-74.1158946, 4.6311287]}, "properties": {"timestamp": 1559073411.0, "p25": 16}}, {"type": "Feature", "geometry": {"type": "Point", "coordinates": [-74.1158903, 4.6311228]}, "properties": {"timestamp": 1559073421.0, "p25": 15}}, {"type": "Feature", "geometry": {"type": "Point", "coordinates": [-74.1158669, 4.6311177]}, "properties": {"timestamp": 1559073431.0, "p25": 15}}, {"type": "Feature", "geometry": {"type": "Point", "coordinates": [-74.1159015, 4.6311349]}, "properties": {"timestamp": 1559073441.0, "p25": 14}}, {"type": "Feature", "geometry": {"type": "Point", "coordinates": [-74.1159012, 4.631144]}, "properties": {"timestamp": 1559073451.0, "p25": 12}}, {"type": "Feature", "geometry": {"type": "Point", "coordinates": [-74.1159015, 4.6311442]}, "properties": {"timestamp": 1559073461.0, "p25": 8}}, {"type": "Feature", "geometry": {"type": "Point", "coordinates": [-74.1159006, 4.6311445]}, "properties": {"timestamp": 1559073523.0, "p25": 11}}, {"type": "Feature", "geometry": {"type": "Point", "coordinates": [-74.1159006, 4.6311445]}, "properties": {"timestamp": 1559073533.0, "p25": 11}}, {"type": "Feature", "geometry": {"type": "Point", "coordinates": [-74.1158951, 4.6311115]}, "properties": {"timestamp": 1559073543.0, "p25": 12}}, {"type": "Feature", "geometry": {"type": "Point", "coordinates": [-74.11588, 4.6311015]}, "properties": {"timestamp": 1559073553.0, "p25": 14}}, {"type": "Feature", "geometry": {"type": "Point", "coordinates": [-74.1158821, 4.6310942]}, "properties": {"timestamp": 1559073563.0, "p25": 14}}, {"type": "Feature", "geometry": {"type": "Point", "coordinates": [-74.1158836, 4.6310927]}, "properties": {"timestamp": 1559073574.0, "p25": 11}}, {"type": "Feature", "geometry": {"type": "Point", "coordinates": [-74.1158829, 4.6310946]}, "properties": {"timestamp": 1559073584.0, "p25": 10}}, {"type": "Feature", "geometry": {"type": "Point", "coordinates": [-74.1158911, 4.6310959]}, "properties": {"timestamp": 1559073594.0, "p25": 10}}, {"type": "Feature", "geometry": {"type": "Point", "coordinates": [-74.115891, 4.6310933]}, "properties": {"timestamp": 1559073604.0, "p25": 10}}, {"type": "Feature", "geometry": {"type": "Point", "coordinates": [-74.1158907, 4.6310931]}, "properties": {"timestamp": 1559073614.0, "p25": 11}}, {"type": "Feature", "geometry": {"type": "Point", "coordinates": [-74.1158911, 4.6310931]}, "properties": {"timestamp": 1559073624.0, "p25": 10}}, {"type": "Feature", "geometry": {"type": "Point", "coordinates": [-74.1158999, 4.631086]}, "properties": {"timestamp": 1559073635.0, "p25": 10}}, {"type": "Feature", "geometry": {"type": "Point", "coordinates": [-74.1159006, 4.6310849]}, "properties": {"timestamp": 1559073645.0, "p25": 11}}, {"type": "Feature", "geometry": {"type": "Point", "coordinates": [-74.1159007, 4.6310848]}, "properties": {"timestamp": 1559073655.0, "p25": 10}}, {"type": "Feature", "geometry": {"type": "Point", "coordinates": [-74.1159007, 4.6310848]}, "properties": {"timestamp": 1559073665.0, "p25": 10}}, {"type": "Feature", "geometry": {"type": "Point", "coordinates": [-74.1159007, 4.6310848]}, "properties": {"timestamp": 1559073675.0, "p25": 11}}, {"type": "Feature", "geometry": {"type": "Point", "coordinates": [-74.1159007, 4.6310848]}, "properties": {"timestamp": 1559073685.0, "p25": 13}}, {"type": "Feature", "geometry": {"type": "Point", "coordinates": [-74.1159007, 4.6310848]}, "properties": {"timestamp": 1559073696.0, "p25": 13}}, {"type": "Feature", "geometry": {"type": "Point", "coordinates": [-74.1159007, 4.6310848]}, "properties": {"timestamp": 1559073706.0, "p25": 14}}, {"type": "Feature", "geometry": {"type": "Point", "coordinates": [-74.1159007, 4.6310848]}, "properties": {"timestamp": 1559073716.0, "p25": 14}}, {"type": "Feature", "geometry": {"type": "Point", "coordinates": [-74.1159007, 4.6310848]}, "properties": {"timestamp": 1559073726.0, "p25": 18}}, {"type": "Feature", "geometry": {"type": "Point", "coordinates": [-74.1159007, 4.6310848]}, "properties": {"timestamp": 1559073736.0, "p25": 20}}, {"type": "Feature", "geometry": {"type": "Point", "coordinates": [-74.1158835, 4.6311078]}, "properties": {"timestamp": 1559073746.0, "p25": 19}}, {"type": "Feature", "geometry": {"type": "Point", "coordinates": [-74.1158624, 4.6311392]}, "properties": {"timestamp": 1559073757.0, "p25": 19}}, {"type": "Feature", "geometry": {"type": "Point", "coordinates": [-74.1158732, 4.6311253]}, "properties": {"timestamp": 1559073767.0, "p25": 19}}, {"type": "Feature", "geometry": {"type": "Point", "coordinates": [-74.1158797, 4.6311178]}, "properties": {"timestamp": 1559073777.0, "p25": 20}}, {"type": "Feature", "geometry": {"type": "Point", "coordinates": [-74.1158806, 4.6311156]}, "properties": {"timestamp": 1559073787.0, "p25": 20}}, {"type": "Feature", "geometry": {"type": "Point", "coordinates": [-74.1158806, 4.6311154]}, "properties": {"timestamp": 1559073797.0, "p25": 19}}, {"type": "Feature", "geometry": {"type": "Point", "coordinates": [-74.1158806, 4.6311151]}, "properties": {"timestamp": 1559073807.0, "p25": 19}}, {"type": "Feature", "geometry": {"type": "Point", "coordinates": [-74.1158807, 4.6311151]}, "properties": {"timestamp": 1559073817.0, "p25": 18}}, {"type": "Feature", "geometry": {"type": "Point", "coordinates": [-74.1158809, 4.6311144]}, "properties": {"timestamp": 1559073828.0, "p25": 17}}, {"type": "Feature", "geometry": {"type": "Point", "coordinates": [-74.1158823, 4.6311152]}, "properties": {"timestamp": 1559073838.0, "p25": 18}}, {"type": "Feature", "geometry": {"type": "Point", "coordinates": [-74.1158909, 4.6311175]}, "properties": {"timestamp": 1559073848.0, "p25": 17}}, {"type": "Feature", "geometry": {"type": "Point", "coordinates": [-74.115896, 4.6311176]}, "properties": {"timestamp": 1559073858.0, "p25": 17}}, {"type": "Feature", "geometry": {"type": "Point", "coordinates": [-74.1158997, 4.6311154]}, "properties": {"timestamp": 1559073868.0, "p25": 15}}, {"type": "Feature", "geometry": {"type": "Point", "coordinates": [-74.1159093, 4.6311102]}, "properties": {"timestamp": 1559073878.0, "p25": 14}}, {"type": "Feature", "geometry": {"type": "Point", "coordinates": [-74.1159083, 4.6311083]}, "properties": {"timestamp": 1559073889.0, "p25": 14}}, {"type": "Feature", "geometry": {"type": "Point", "coordinates": [-74.115893, 4.6310719]}, "properties": {"timestamp": 1559074559.0, "p25": 12}}, {"type": "Feature", "geometry": {"type": "Point", "coordinates": [-74.1158945, 4.6310716]}, "properties": {"timestamp": 1559074569.0, "p25": 12}}, {"type": "Feature", "geometry": {"type": "Point", "coordinates": [-74.1158951, 4.6310715]}, "properties": {"timestamp": 1559074579.0, "p25": 11}}, {"type": "Feature", "geometry": {"type": "Point", "coordinates": [-74.1158951, 4.6310715]}, "properties": {"timestamp": 1559074590.0, "p25": 9}}, {"type": "Feature", "geometry": {"type": "Point", "coordinates": [-74.1158928, 4.6310736]}, "properties": {"timestamp": 1559074600.0, "p25": 9}}, {"type": "Feature", "geometry": {"type": "Point", "coordinates": [-74.1158925, 4.6310733]}, "properties": {"timestamp": 1559074610.0, "p25": 9}}, {"type": "Feature", "geometry": {"type": "Point", "coordinates": [-74.1158927, 4.6310724]}, "properties": {"timestamp": 1559074620.0, "p25": 11}}, {"type": "Feature", "geometry": {"type": "Point", "coordinates": [-74.115883, 4.6310777]}, "properties": {"timestamp": 1559074630.0, "p25": 13}}, {"type": "Feature", "geometry": {"type": "Point", "coordinates": [-74.1158683, 4.6310582]}, "properties": {"timestamp": 1559074640.0, "p25": 12}}, {"type": "Feature", "geometry": {"type": "Point", "coordinates": [-74.1158663, 4.6310577]}, "properties": {"timestamp": 1559074651.0, "p25": 12}}, {"type": "Feature", "geometry": {"type": "Point", "coordinates": [-74.1158661, 4.6310577]}, "properties": {"timestamp": 1559074661.0, "p25": 12}}, {"type": "Feature", "geometry": {"type": "Point", "coordinates": [-74.1158663, 4.6310573]}, "properties": {"timestamp": 1559074671.0, "p25": 12}}, {"type": "Feature", "geometry": {"type": "Point", "coordinates": [-74.1158717, 4.6310611]}, "properties": {"timestamp": 1559074681.0, "p25": 13}}, {"type": "Feature", "geometry": {"type": "Point", "coordinates": [-74.1159156, 4.6310511]}, "properties": {"timestamp": 1559072628.0, "p25": 17}}, {"type": "Feature", "geometry": {"type": "Point", "coordinates": [-74.1159168, 4.6310514]}, "properties": {"timestamp": 1559072638.0, "p25": 15}}, {"type": "Feature", "geometry": {"type": "Point", "coordinates": [-74.115918, 4.6310538]}, "properties": {"timestamp": 1559072649.0, "p25": 11}}, {"type": "Feature", "geometry": {"type": "Point", "coordinates": [-74.1159198, 4.6310594]}, "properties": {"timestamp": 1559072659.0, "p25": 11}}, {"type": "Feature", "geometry": {"type": "Point", "coordinates": [-74.1159221, 4.631065]}, "properties": {"timestamp": 1559072669.0, "p25": 10}}, {"type": "Feature", "geometry": {"type": "Point", "coordinates": [-74.1159229, 4.6310659]}, "properties": {"timestamp": 1559072679.0, "p25": 8}}, {"type": "Feature", "geometry": {"type": "Point", "coordinates": [-74.115924, 4.6310667]}, "properties": {"timestamp": 1559072689.0, "p25": 10}}, {"type": "Feature", "geometry": {"type": "Point", "coordinates": [-74.115924, 4.6310667]}, "properties": {"timestamp": 1559072699.0, "p25": 9}}, {"type": "Feature", "geometry": {"type": "Point", "coordinates": [-74.115924, 4.6310667]}, "properties": {"timestamp": 1559072710.0, "p25": 10}}, {"type": "Feature", "geometry": {"type": "Point", "coordinates": [-74.115924, 4.6310667]}, "properties": {"timestamp": 1559072720.0, "p25": 11}}, {"type": "Feature", "geometry": {"type": "Point", "coordinates": [-74.1159197, 4.6310654]}, "properties": {"timestamp": 1559072730.0, "p25": 13}}, {"type": "Feature", "geometry": {"type": "Point", "coordinates": [-74.1159174, 4.6310651]}, "properties": {"timestamp": 1559072740.0, "p25": 13}}, {"type": "Feature", "geometry": {"type": "Point", "coordinates": [-74.1159057, 4.6310828]}, "properties": {"timestamp": 1559072750.0, "p25": 12}}, {"type": "Feature", "geometry": {"type": "Point", "coordinates": [-74.1159095, 4.6310636]}, "properties": {"timestamp": 1559072760.0, "p25": 12}}, {"type": "Feature", "geometry": {"type": "Point", "coordinates": [-74.1159087, 4.6310611]}, "properties": {"timestamp": 1559072771.0, "p25": 13}}, {"type": "Feature", "geometry": {"type": "Point", "coordinates": [-74.1159087, 4.6310611]}, "properties": {"timestamp": 1559072781.0, "p25": 12}}, {"type": "Feature", "geometry": {"type": "Point", "coordinates": [-74.1159087, 4.6310611]}, "properties": {"timestamp": 1559072791.0, "p25": 12}}, {"type": "Feature", "geometry": {"type": "Point", "coordinates": [-74.1159087, 4.6310611]}, "properties": {"timestamp": 1559072801.0, "p25": 12}}, {"type": "Feature", "geometry": {"type": "Point", "coordinates": [-74.1159087, 4.6310611]}, "properties": {"timestamp": 1559072811.0, "p25": 14}}, {"type": "Feature", "geometry": {"type": "Point", "coordinates": [-74.1159036, 4.6310551]}, "properties": {"timestamp": 1559072821.0, "p25": 14}}, {"type": "Feature", "geometry": {"type": "Point", "coordinates": [-74.1159032, 4.6310526]}, "properties": {"timestamp": 1559072832.0, "p25": 12}}, {"type": "Feature", "geometry": {"type": "Point", "coordinates": [-74.1159147, 4.6310542]}, "properties": {"timestamp": 1559072842.0, "p25": 13}}, {"type": "Feature", "geometry": {"type": "Point", "coordinates": [-74.1159179, 4.631053]}, "properties": {"timestamp": 1559072852.0, "p25": 15}}, {"type": "Feature", "geometry": {"type": "Point", "coordinates": [-74.115918, 4.6310529]}, "properties": {"timestamp": 1559072862.0, "p25": 17}}, {"type": "Feature", "geometry": {"type": "Point", "coordinates": [-74.115926, 4.631058]}, "properties": {"timestamp": 1559072872.0, "p25": 17}}, {"type": "Feature", "geometry": {"type": "Point", "coordinates": [-74.1159267, 4.6310586]}, "properties": {"timestamp": 1559072882.0, "p25": 15}}, {"type": "Feature", "geometry": {"type": "Point", "coordinates": [-74.1159289, 4.6310615]}, "properties": {"timestamp": 1559072892.0, "p25": 14}}, {"type": "Feature", "geometry": {"type": "Point", "coordinates": [-74.1159294, 4.6310621]}, "properties": {"timestamp": 1559072903.0, "p25": 14}}, {"type": "Feature", "geometry": {"type": "Point", "coordinates": [-74.1159294, 4.6310621]}, "properties": {"timestamp": 1559072913.0, "p25": 13}}, {"type": "Feature", "geometry": {"type": "Point", "coordinates": [-74.1159202, 4.6310735]}, "properties": {"timestamp": 1559072923.0, "p25": 13}}, {"type": "Feature", "geometry": {"type": "Point", "coordinates": [-74.1159272, 4.6310648]}, "properties": {"timestamp": 1559072933.0, "p25": 13}}, {"type": "Feature", "geometry": {"type": "Point", "coordinates": [-74.1159293, 4.6310622]}, "properties": {"timestamp": 1559072943.0, "p25": 11}}, {"type": "Feature", "geometry": {"type": "Point", "coordinates": [-74.1159294, 4.6310621]}, "properties": {"timestamp": 1559072954.0, "p25": 13}}, {"type": "Feature", "geometry": {"type": "Point", "coordinates": [-74.1159294, 4.6310621]}, "properties": {"timestamp": 1559072964.0, "p25": 14}}, {"type": "Feature", "geometry": {"type": "Point", "coordinates": [-74.1159294, 4.6310621]}, "properties": {"timestamp": 1559072974.0, "p25": 15}}, {"type": "Feature", "geometry": {"type": "Point", "coordinates": [-74.115932, 4.631064]}, "properties": {"timestamp": 1559072984.0, "p25": 15}}, {"type": "Feature", "geometry": {"type": "Point", "coordinates": [-74.1159327, 4.631065]}, "properties": {"timestamp": 1559072994.0, "p25": 15}}, {"type": "Feature", "geometry": {"type": "Point", "coordinates": [-74.1159339, 4.631071]}, "properties": {"timestamp": 1559073004.0, "p25": 16}}, {"type": "Feature", "geometry": {"type": "Point", "coordinates": [-74.1159346, 4.6310719]}, "properties": {"timestamp": 1559073014.0, "p25": 14}}, {"type": "Feature", "geometry": {"type": "Point", "coordinates": [-74.1159346, 4.6310719]}, "properties": {"timestamp": 1559073025.0, "p25": 15}}, {"type": "Feature", "geometry": {"type": "Point", "coordinates": [-74.115914, 4.6310905]}, "properties": {"timestamp": 1559073035.0, "p25": 16}}, {"type": "Feature", "geometry": {"type": "Point", "coordinates": [-74.1159343, 4.6310721]}, "properties": {"timestamp": 1559073045.0, "p25": 17}}, {"type": "Feature", "geometry": {"type": "Point", "coordinates": [-74.1159331, 4.6310716]}, "properties": {"timestamp": 1559073055.0, "p25": 17}}, {"type": "Feature", "geometry": {"type": "Point", "coordinates": [-74.1159323, 4.6310714]}, "properties": {"timestamp": 1559073065.0, "p25": 17}}, {"type": "Feature", "geometry": {"type": "Point", "coordinates": [-74.1159322, 4.6310714]}, "properties": {"timestamp": 1559073075.0, "p25": 14}}, {"type": "Feature", "geometry": {"type": "Point", "coordinates": [-74.1159322, 4.6310714]}, "properties": {"timestamp": 1559073085.0, "p25": 13}}, {"type": "Feature", "geometry": {"type": "Point", "coordinates": [-74.1159322, 4.6310714]}, "properties": {"timestamp": 1559073096.0, "p25": 17}}, {"type": "Feature", "geometry": {"type": "Point", "coordinates": [-74.1159345, 4.6310737]}, "properties": {"timestamp": 1559073106.0, "p25": 18}}, {"type": "Feature", "geometry": {"type": "Point", "coordinates": [-74.1159313, 4.631069]}, "properties": {"timestamp": 1559073116.0, "p25": 19}}, {"type": "Feature", "geometry": {"type": "Point", "coordinates": [-74.1159305, 4.6310681]}, "properties": {"timestamp": 1559073126.0, "p25": 20}}, {"type": "Feature", "geometry": {"type": "Point", "coordinates": [-74.1159287, 4.6310684]}, "properties": {"timestamp": 1559073136.0, "p25": 20}}, {"type": "Feature", "geometry": {"type": "Point", "coordinates": [-74.1159224, 4.6310744]}, "properties": {"timestamp": 1559073146.0, "p25": 22}}, {"type": "Feature", "geometry": {"type": "Point", "coordinates": [-74.1158948, 4.6310759]}, "properties": {"timestamp": 1559073157.0, "p25": 34}}, {"type": "Feature", "geometry": {"type": "Point", "coordinates": [-74.115833, 4.6310383]}, "properties": {"timestamp": 1559073167.0, "p25": 32}}, {"type": "Feature", "geometry": {"type": "Point", "coordinates": [-74.1158877, 4.6311122]}, "properties": {"timestamp": 1559073177.0, "p25": 29}}, {"type": "Feature", "geometry": {"type": "Point", "coordinates": [-74.1159065, 4.631108]}, "properties": {"timestamp": 1559073899.0, "p25": 15}}, {"type": "Feature", "geometry": {"type": "Point", "coordinates": [-74.1159019, 4.6311048]}, "properties": {"timestamp": 1559073909.0, "p25": 16}}, {"type": "Feature", "geometry": {"type": "Point", "coordinates": [-74.1159032, 4.6311032]}, "properties": {"timestamp": 1559073919.0, "p25": 15}}, {"type": "Feature", "geometry": {"type": "Point", "coordinates": [-74.1159045, 4.6311008]}, "properties": {"timestamp": 1559073929.0, "p25": 14}}, {"type": "Feature", "geometry": {"type": "Point", "coordinates": [-74.1159045, 4.6310995]}, "properties": {"timestamp": 1559073939.0, "p25": 14}}, {"type": "Feature", "geometry": {"type": "Point", "coordinates": [-74.1158961, 4.6310956]}, "properties": {"timestamp": 1559073950.0, "p25": 13}}, {"type": "Feature", "geometry": {"type": "Point", "coordinates": [-74.1158903, 4.6310771]}, "properties": {"timestamp": 1559073960.0, "p25": 12}}, {"type": "Feature", "geometry": {"type": "Point", "coordinates": [-74.1158922, 4.631078]}, "properties": {"timestamp": 1559073970.0, "p25": 12}}, {"type": "Feature", "geometry": {"type": "Point", "coordinates": [-74.1158967, 4.6310772]}, "properties": {"timestamp": 1559073980.0, "p25": 13}}, {"type": "Feature", "geometry": {"type": "Point", "coordinates": [-74.1159031, 4.6310748]}, "properties": {"timestamp": 1559073990.0, "p25": 14}}, {"type": "Feature", "geometry": {"type": "Point", "coordinates": [-74.1159036, 4.6310743]}, "properties": {"timestamp": 1559074000.0, "p25": 13}}, {"type": "Feature", "geometry": {"type": "Point", "coordinates": [-74.1159043, 4.6310746]}, "properties": {"timestamp": 1559074011.0, "p25": 13}}, {"type": "Feature", "geometry": {"type": "Point", "coordinates": [-74.1159045, 4.6310746]}, "properties": {"timestamp": 1559074021.0, "p25": 13}}, {"type": "Feature", "geometry": {"type": "Point", "coordinates": [-74.1159045, 4.6310745]}, "properties": {"timestamp": 1559074031.0, "p25": 14}}, {"type": "Feature", "geometry": {"type": "Point", "coordinates": [-74.1159045, 4.6310744]}, "properties": {"timestamp": 1559074041.0, "p25": 15}}, {"type": "Feature", "geometry": {"type": "Point", "coordinates": [-74.1159045, 4.6310743]}, "properties": {"timestamp": 1559074051.0, "p25": 15}}, {"type": "Feature", "geometry": {"type": "Point", "coordinates": [-74.1159045, 4.6310742]}, "properties": {"timestamp": 1559074061.0, "p25": 15}}, {"type": "Feature", "geometry": {"type": "Point", "coordinates": [-74.1159045, 4.6310741]}, "properties": {"timestamp": 1559074071.0, "p25": 14}}, {"type": "Feature", "geometry": {"type": "Point", "coordinates": [-74.1159045, 4.631074]}, "properties": {"timestamp": 1559074082.0, "p25": 15}}, {"type": "Feature", "geometry": {"type": "Point", "coordinates": [-74.1159045, 4.631074]}, "properties": {"timestamp": 1559074092.0, "p25": 14}}, {"type": "Feature", "geometry": {"type": "Point", "coordinates": [-74.1159045, 4.6310739]}, "properties": {"timestamp": 1559074102.0, "p25": 13}}, {"type": "Feature", "geometry": {"type": "Point", "coordinates": [-74.1159046, 4.6310739]}, "properties": {"timestamp": 1559074112.0, "p25": 15}}, {"type": "Feature", "geometry": {"type": "Point", "coordinates": [-74.1159046, 4.6310738]}, "properties": {"timestamp": 1559074122.0, "p25": 15}}, {"type": "Feature", "geometry": {"type": "Point", "coordinates": [-74.1159046, 4.6310738]}, "properties": {"timestamp": 1559074132.0, "p25": 14}}, {"type": "Feature", "geometry": {"type": "Point", "coordinates": [-74.1159047, 4.6310738]}, "properties": {"timestamp": 1559074143.0, "p25": 14}}, {"type": "Feature", "geometry": {"type": "Point", "coordinates": [-74.1159045, 4.6310739]}, "properties": {"timestamp": 1559074153.0, "p25": 14}}, {"type": "Feature", "geometry": {"type": "Point", "coordinates": [-74.1159043, 4.6310739]}, "properties": {"timestamp": 1559074163.0, "p25": 12}}, {"type": "Feature", "geometry": {"type": "Point", "coordinates": [-74.1159058, 4.6310742]}, "properties": {"timestamp": 1559074173.0, "p25": 10}}, {"type": "Feature", "geometry": {"type": "Point", "coordinates": [-74.1158959, 4.6310631]}, "properties": {"timestamp": 1559074183.0, "p25": 11}}, {"type": "Feature", "geometry": {"type": "Point", "coordinates": [-74.1158932, 4.6310593]}, "properties": {"timestamp": 1559074193.0, "p25": 11}}, {"type": "Feature", "geometry": {"type": "Point", "coordinates": [-74.115893, 4.6310589]}, "properties": {"timestamp": 1559074204.0, "p25": 11}}, {"type": "Feature", "geometry": {"type": "Point", "coordinates": [-74.1159014, 4.631065]}, "properties": {"timestamp": 1559074214.0, "p25": 11}}, {"type": "Feature", "geometry": {"type": "Point", "coordinates": [-74.1159034, 4.6310669]}, "properties": {"timestamp": 1559074224.0, "p25": 12}}, {"type": "Feature", "geometry": {"type": "Point", "coordinates": [-74.1159036, 4.6310669]}, "properties": {"timestamp": 1559074234.0, "p25": 10}}, {"type": "Feature", "geometry": {"type": "Point", "coordinates": [-74.1159035, 4.6310669]}, "properties": {"timestamp": 1559074244.0, "p25": 9}}, {"type": "Feature", "geometry": {"type": "Point", "coordinates": [-74.1159035, 4.6310669]}, "properties": {"timestamp": 1559074254.0, "p25": 9}}, {"type": "Feature", "geometry": {"type": "Point", "coordinates": [-74.1159034, 4.6310669]}, "properties": {"timestamp": 1559074265.0, "p25": 8}}, {"type": "Feature", "geometry": {"type": "Point", "coordinates": [-74.1159034, 4.6310669]}, "properties": {"timestamp": 1559074275.0, "p25": 9}}, {"type": "Feature", "geometry": {"type": "Point", "coordinates": [-74.1159033, 4.6310669]}, "properties": {"timestamp": 1559074285.0, "p25": 9}}, {"type": "Feature", "geometry": {"type": "Point", "coordinates": [-74.1159033, 4.631067]}, "properties": {"timestamp": 1559074295.0, "p25": 10}}, {"type": "Feature", "geometry": {"type": "Point", "coordinates": [-74.1159048, 4.6310668]}, "properties": {"timestamp": 1559074305.0, "p25": 11}}, {"type": "Feature", "geometry": {"type": "Point", "coordinates": [-74.1159013, 4.6310587]}, "properties": {"timestamp": 1559074315.0, "p25": 9}}, {"type": "Feature", "geometry": {"type": "Point", "coordinates": [-74.1158936, 4.6310564]}, "properties": {"timestamp": 1559074325.0, "p25": 8}}, {"type": "Feature", "geometry": {"type": "Point", "coordinates": [-74.1158929, 4.6310574]}, "properties": {"timestamp": 1559074336.0, "p25": 8}}, {"type": "Feature", "geometry": {"type": "Point", "coordinates": [-74.1158938, 4.631055]}, "properties": {"timestamp": 1559074346.0, "p25": 8}}, {"type": "Feature", "geometry": {"type": "Point", "coordinates": [-74.1158878, 4.6310586]}, "properties": {"timestamp": 1559074356.0, "p25": 8}}, {"type": "Feature", "geometry": {"type": "Point", "coordinates": [-74.1158852, 4.6310603]}, "properties": {"timestamp": 1559074366.0, "p25": 8}}, {"type": "Feature", "geometry": {"type": "Point", "coordinates": [-74.1158921, 4.631068]}, "properties": {"timestamp": 1559074376.0, "p25": 8}}, {"type": "Feature", "geometry": {"type": "Point", "coordinates": [-74.1158914, 4.6310595]}, "properties": {"timestamp": 1559074386.0, "p25": 7}}, {"type": "Feature", "geometry": {"type": "Point", "coordinates": [-74.1158911, 4.6310591]}, "properties": {"timestamp": 1559074397.0, "p25": 9}}, {"type": "Feature", "geometry": {"type": "Point", "coordinates": [-74.1158911, 4.6310591]}, "properties": {"timestamp": 1559074407.0, "p25": 8}}, {"type": "Feature", "geometry": {"type": "Point", "coordinates": [-74.1158911, 4.6310591]}, "properties": {"timestamp": 1559074417.0, "p25": 8}}, {"type": "Feature", "geometry": {"type": "Point", "coordinates": [-74.1158911, 4.6310591]}, "properties": {"timestamp": 1559074427.0, "p25": 8}}, {"type": "Feature", "geometry": {"type": "Point", "coordinates": [-74.1158899, 4.6310635]}, "properties": {"timestamp": 1559074437.0, "p25": 11}}, {"type": "Feature", "geometry": {"type": "Point", "coordinates": [-74.1158899, 4.6310646]}, "properties": {"timestamp": 1559074447.0, "p25": 10}}, {"type": "Feature", "geometry": {"type": "Point", "coordinates": [-74.1158899, 4.6310647]}, "properties": {"timestamp": 1559074458.0, "p25": 9}}, {"type": "Feature", "geometry": {"type": "Point", "coordinates": [-74.1158906, 4.6310656]}, "properties": {"timestamp": 1559074468.0, "p25": 8}}, {"type": "Feature", "geometry": {"type": "Point", "coordinates": [-74.1158911, 4.6310655]}, "properties": {"timestamp": 1559074478.0, "p25": 11}}, {"type": "Feature", "geometry": {"type": "Point", "coordinates": [-74.1158933, 4.6310687]}, "properties": {"timestamp": 1559074488.0, "p25": 11}}, {"type": "Feature", "geometry": {"type": "Point", "coordinates": [-74.1158913, 4.6310656]}, "properties": {"timestamp": 1559074498.0, "p25": 11}}, {"type": "Feature", "geometry": {"type": "Point", "coordinates": [-74.1158897, 4.6310675]}, "properties": {"timestamp": 1559074508.0, "p25": 11}}, {"type": "Feature", "geometry": {"type": "Point", "coordinates": [-74.1158887, 4.6310713]}, "properties": {"timestamp": 1559074518.0, "p25": 10}}, {"type": "Feature", "geometry": {"type": "Point", "coordinates": [-74.1158925, 4.6310718]}, "properties": {"timestamp": 1559074529.0, "p25": 10}}, {"type": "Feature", "geometry": {"type": "Point", "coordinates": [-74.115893, 4.6310719]}, "properties": {"timestamp": 1559074539.0, "p25": 11}}, {"type": "Feature", "geometry": {"type": "Point", "coordinates": [-74.115893, 4.6310719]}, "properties": {"timestamp": 1559074549.0, "p25": 13}}, {"type": "Feature", "geometry": {"type": "Point", "coordinates": [-74.1158804, 4.6310649]}, "properties": {"timestamp": 1559072287.0, "p25": 18}}, {"type": "Feature", "geometry": {"type": "Point", "coordinates": [-74.1158824, 4.6310444]}, "properties": {"timestamp": 1559072292.0, "p25": 18}}, {"type": "Feature", "geometry": {"type": "Point", "coordinates": [-74.1158884, 4.6310412]}, "properties": {"timestamp": 1559072297.0, "p25": 17}}, {"type": "Feature", "geometry": {"type": "Point", "coordinates": [-74.1158924, 4.6310397]}, "properties": {"timestamp": 1559072302.0, "p25": 13}}, {"type": "Feature", "geometry": {"type": "Point", "coordinates": [-74.1158938, 4.6310361]}, "properties": {"timestamp": 1559072307.0, "p25": 11}}, {"type": "Feature", "geometry": {"type": "Point", "coordinates": [-74.115893, 4.6310351]}, "properties": {"timestamp": 1559072313.0, "p25": 10}}, {"type": "Feature", "geometry": {"type": "Point", "coordinates": [-74.1158927, 4.6310349]}, "properties": {"timestamp": 1559072318.0, "p25": 9}}, {"type": "Feature", "geometry": {"type": "Point", "coordinates": [-74.1158926, 4.6310353]}, "properties": {"timestamp": 1559072323.0, "p25": 10}}, {"type": "Feature", "geometry": {"type": "Point", "coordinates": [-74.1158929, 4.6310359]}, "properties": {"timestamp": 1559072328.0, "p25": 9}}, {"type": "Feature", "geometry": {"type": "Point", "coordinates": [-74.115893, 4.631036]}, "properties": {"timestamp": 1559072333.0, "p25": 8}}, {"type": "Feature", "geometry": {"type": "Point", "coordinates": [-74.1158936, 4.6310363]}, "properties": {"timestamp": 1559072338.0, "p25": 8}}, {"type": "Feature", "geometry": {"type": "Point", "coordinates": [-74.1158943, 4.6310369]}, "properties": {"timestamp": 1559072343.0, "p25": 10}}, {"type": "Feature", "geometry": {"type": "Point", "coordinates": [-74.1158945, 4.6310371]}, "properties": {"timestamp": 1559072348.0, "p25": 10}}, {"type": "Feature", "geometry": {"type": "Point", "coordinates": [-74.1158945, 4.6310371]}, "properties": {"timestamp": 1559072354.0, "p25": 10}}, {"type": "Feature", "geometry": {"type": "Point", "coordinates": [-74.1158954, 4.6310373]}, "properties": {"timestamp": 1559072359.0, "p25": 10}}, {"type": "Feature", "geometry": {"type": "Point", "coordinates": [-74.1159013, 4.631036]}, "properties": {"timestamp": 1559072364.0, "p25": 10}}, {"type": "Feature", "geometry": {"type": "Point", "coordinates": [-74.1159034, 4.6310357]}, "properties": {"timestamp": 1559072369.0, "p25": 10}}, {"type": "Feature", "geometry": {"type": "Point", "coordinates": [-74.1159069, 4.6310382]}, "properties": {"timestamp": 1559072374.0, "p25": 11}}, {"type": "Feature", "geometry": {"type": "Point", "coordinates": [-74.1159063, 4.6310368]}, "properties": {"timestamp": 1559072379.0, "p25": 11}}, {"type": "Feature", "geometry": {"type": "Point", "coordinates": [-74.1159061, 4.6310365]}, "properties": {"timestamp": 1559072384.0, "p25": 10}}, {"type": "Feature", "geometry": {"type": "Point", "coordinates": [-74.1159058, 4.6310369]}, "properties": {"timestamp": 1559072389.0, "p25": 10}}, {"type": "Feature", "geometry": {"type": "Point", "coordinates": [-74.1159062, 4.631037]}, "properties": {"timestamp": 1559072395.0, "p25": 11}}, {"type": "Feature", "geometry": {"type": "Point", "coordinates": [-74.1159063, 4.631037]}, "properties": {"timestamp": 1559072400.0, "p25": 13}}, {"type": "Feature", "geometry": {"type": "Point", "coordinates": [-74.1159063, 4.631037]}, "properties": {"timestamp": 1559072405.0, "p25": 14}}, {"type": "Feature", "geometry": {"type": "Point", "coordinates": [-74.1159027, 4.6310395]}, "properties": {"timestamp": 1559072410.0, "p25": 14}}, {"type": "Feature", "geometry": {"type": "Point", "coordinates": [-74.1159074, 4.6310355]}, "properties": {"timestamp": 1559072417.0, "p25": 12}}, {"type": "Feature", "geometry": {"type": "Point", "coordinates": [-74.1159079, 4.631035]}, "properties": {"timestamp": 1559072427.0, "p25": 11}}, {"type": "Feature", "geometry": {"type": "Point", "coordinates": [-74.1159079, 4.631035]}, "properties": {"timestamp": 1559072435.0, "p25": 11}}, {"type": "Feature", "geometry": {"type": "Point", "coordinates": [-74.1159079, 4.631035]}, "properties": {"timestamp": 1559072445.0, "p25": 11}}, {"type": "Feature", "geometry": {"type": "Point", "coordinates": [-74.1159079, 4.631035]}, "properties": {"timestamp": 1559072456.0, "p25": 13}}, {"type": "Feature", "geometry": {"type": "Point", "coordinates": [-74.1159079, 4.631035]}, "properties": {"timestamp": 1559072466.0, "p25": 11}}, {"type": "Feature", "geometry": {"type": "Point", "coordinates": [-74.1159079, 4.631035]}, "properties": {"timestamp": 1559072476.0, "p25": 11}}, {"type": "Feature", "geometry": {"type": "Point", "coordinates": [-74.1159079, 4.631035]}, "properties": {"timestamp": 1559072486.0, "p25": 10}}, {"type": "Feature", "geometry": {"type": "Point", "coordinates": [-74.1159079, 4.631035]}, "properties": {"timestamp": 1559072496.0, "p25": 11}}, {"type": "Feature", "geometry": {"type": "Point", "coordinates": [-74.1159079, 4.631035]}, "properties": {"timestamp": 1559072506.0, "p25": 9}}, {"type": "Feature", "geometry": {"type": "Point", "coordinates": [-74.1159079, 4.631035]}, "properties": {"timestamp": 1559072517.0, "p25": 8}}]