[{"geometry": {"coordinates": [-74.1362163, 4.6017542], "type": "Point"}, "properties": {"timestamp": 1552750464.0, "p25": 17}, "type": "Feature"}, {"geometry": {"coordinates": [-74.1362202, 4.6017387], "type": "Point"}, "properties": {"timestamp": 1552750469.0, "p25": 15}, "type": "Feature"}, {"geometry": {"coordinates": [-74.1362202, 4.6017387], "type": "Point"}, "properties": {"timestamp": 1552750475.0, "p25": 14}, "type": "Feature"}, {"geometry": {"coordinates": [-74.1362274, 4.6017468], "type": "Point"}, "properties": {"timestamp": 1552750480.0, "p25": 13}, "type": "Feature"}, {"geometry": {"coordinates": [-74.1362274, 4.6017468], "type": "Point"}, "properties": {"timestamp": 1552750485.0, "p25": 12}, "type": "Feature"}, {"geometry": {"coordinates": [-74.1362181, 4.6017454], "type": "Point"}, "properties": {"timestamp": 1552750490.0, "p25": 11}, "type": "Feature"}, {"geometry": {"coordinates": [-74.1362181, 4.6017454], "type": "Point"}, "properties": {"timestamp": 1552750495.0, "p25": 11}, "type": "Feature"}, {"geometry": {"coordinates": [-74.1362254, 4.6017362], "type": "Point"}, "properties": {"timestamp": 1552750500.0, "p25": 12}, "type": "Feature"}, {"geometry": {"coordinates": [-74.1362254, 4.6017362], "type": "Point"}, "properties": {"timestamp": 1552750505.0, "p25": 12}, "type": "Feature"}, {"geometry": {"coordinates": [-74.1362199, 4.601739], "type": "Point"}, "properties": {"timestamp": 1552750510.0, "p25": 11}, "type": "Feature"}, {"geometry": {"coordinates": [-74.1362199, 4.601739], "type": "Point"}, "properties": {"timestamp": 1552750515.0, "p25": 10}, "type": "Feature"}, {"geometry": {"coordinates": [-74.1362139, 4.6017387], "type": "Point"}, "properties": {"timestamp": 1552750520.0, "p25": 10}, "type": "Feature"}, {"geometry": {"coordinates": [-74.1362139, 4.6017387], "type": "Point"}, "properties": {"timestamp": 1552750526.0, "p25": 11}, "type": "Feature"}, {"geometry": {"coordinates": [-74.1362133, 4.6017388], "type": "Point"}, "properties": {"timestamp": 1552750531.0, "p25": 11}, "type": "Feature"}, {"geometry": {"coordinates": [-74.1362133, 4.6017388], "type": "Point"}, "properties": {"timestamp": 1552750536.0, "p25": 12}, "type": "Feature"}, {"geometry": {"coordinates": [-74.1362146, 4.6017096], "type": "Point"}, "properties": {"timestamp": 1552750541.0, "p25": 13}, "type": "Feature"}, {"geometry": {"coordinates": [-74.1362146, 4.6017096], "type": "Point"}, "properties": {"timestamp": 1552750546.0, "p25": 11}, "type": "Feature"}, {"geometry": {"coordinates": [-74.1362183, 4.6017094], "type": "Point"}, "properties": {"timestamp": 1552750551.0, "p25": 11}, "type": "Feature"}, {"geometry": {"coordinates": [-74.1362183, 4.6017094], "type": "Point"}, "properties": {"timestamp": 1552750556.0, "p25": 10}, "type": "Feature"}, {"geometry": {"coordinates": [-74.1362127, 4.6017419], "type": "Point"}, "properties": {"timestamp": 1552750561.0, "p25": 10}, "type": "Feature"}, {"geometry": {"coordinates": [-74.1362127, 4.6017419], "type": "Point"}, "properties": {"timestamp": 1552750566.0, "p25": 11}, "type": "Feature"}, {"geometry": {"coordinates": [-74.1362133, 4.6017284], "type": "Point"}, "properties": {"timestamp": 1552750572.0, "p25": 12}, "type": "Feature"}, {"geometry": {"coordinates": [-74.1362133, 4.6017284], "type": "Point"}, "properties": {"timestamp": 1552750577.0, "p25": 12}, "type": "Feature"}, {"geometry": {"coordinates": [-74.1362306, 4.6016877], "type": "Point"}, "properties": {"timestamp": 1552750582.0, "p25": 12}, "type": "Feature"}, {"geometry": {"coordinates": [-74.1362306, 4.6016877], "type": "Point"}, "properties": {"timestamp": 1552750587.0, "p25": 12}, "type": "Feature"}, {"geometry": {"coordinates": [-74.1362306, 4.6016877], "type": "Point"}, "properties": {"timestamp": 1552750592.0, "p25": 13}, "type": "Feature"}, {"geometry": {"coordinates": [-74.1362562, 4.6016225], "type": "Point"}, "properties": {"timestamp": 1552750597.0, "p25": 13}, "type": "Feature"}, {"geometry": {"coordinates": [-74.13636, 4.6015663], "type": "Point"}, "properties": {"timestamp": 1552750602.0, "p25": 12}, "type": "Feature"}, {"geometry": {"coordinates": [-74.13636, 4.6015663], "type": "Point"}, "properties": {"timestamp": 1552750607.0, "p25": 12}, "type": "Feature"}, {"geometry": {"coordinates": [-74.1362719, 4.6015637], "type": "Point"}, "properties": {"timestamp": 1552750613.0, "p25": 12}, "type": "Feature"}, {"geometry": {"coordinates": [-74.1362719, 4.6015637], "type": "Point"}, "properties": {"timestamp": 1552750618.0, "p25": 12}, "type": "Feature"}, {"geometry": {"coordinates": [-74.1361799, 4.6015243], "type": "Point"}, "properties": {"timestamp": 1552750623.0, "p25": 12}, "type": "Feature"}, {"geometry": {"coordinates": [-74.1361799, 4.6015243], "type": "Point"}, "properties": {"timestamp": 1552750628.0, "p25": 11}, "type": "Feature"}, {"geometry": {"coordinates": [-74.1361739, 4.601507], "type": "Point"}, "properties": {"timestamp": 1552750633.0, "p25": 11}, "type": "Feature"}, {"geometry": {"coordinates": [-74.1361739, 4.601507], "type": "Point"}, "properties": {"timestamp": 1552750638.0, "p25": 10}, "type": "Feature"}, {"geometry": {"coordinates": [-74.1361094, 4.6014947], "type": "Point"}, "properties": {"timestamp": 1552750643.0, "p25": 10}, "type": "Feature"}, {"geometry": {"coordinates": [-74.1361094, 4.6014947], "type": "Point"}, "properties": {"timestamp": 1552750649.0, "p25": 11}, "type": "Feature"}, {"geometry": {"coordinates": [-74.136082, 4.6015225], "type": "Point"}, "properties": {"timestamp": 1552750654.0, "p25": 11}, "type": "Feature"}, {"geometry": {"coordinates": [-74.136082, 4.6015225], "type": "Point"}, "properties": {"timestamp": 1552750659.0, "p25": 11}, "type": "Feature"}, {"geometry": {"coordinates": [-74.1360772, 4.601513], "type": "Point"}, "properties": {"timestamp": 1552750664.0, "p25": 10}, "type": "Feature"}, {"geometry": {"coordinates": [-74.1360772, 4.601513], "type": "Point"}, "properties": {"timestamp": 1552750669.0, "p25": 10}, "type": "Feature"}, {"geometry": {"coordinates": [-74.1360782, 4.6015292], "type": "Point"}, "properties": {"timestamp": 1552750674.0, "p25": 10}, "type": "Feature"}, {"geometry": {"coordinates": [-74.1360782, 4.6015292], "type": "Point"}, "properties": {"timestamp": 1552750679.0, "p25": 11}, "type": "Feature"}, {"geometry": {"coordinates": [-74.1360648, 4.6015129], "type": "Point"}, "properties": {"timestamp": 1552750684.0, "p25": 12}, "type": "Feature"}, {"geometry": {"coordinates": [-74.1360648, 4.6015129], "type": "Point"}, "properties": {"timestamp": 1552750689.0, "p25": 12}, "type": "Feature"}, {"geometry": {"coordinates": [-74.1360801, 4.6015061], "type": "Point"}, "properties": {"timestamp": 1552750695.0, "p25": 11}, "type": "Feature"}, {"geometry": {"coordinates": [-74.1360801, 4.6015061], "type": "Point"}, "properties": {"timestamp": 1552750700.0, "p25": 11}, "type": "Feature"}, {"geometry": {"coordinates": [-74.1361066, 4.6014893], "type": "Point"}, "properties": {"timestamp": 1552750705.0, "p25": 11}, "type": "Feature"}, {"geometry": {"coordinates": [-74.1361066, 4.6014893], "type": "Point"}, "properties": {"timestamp": 1552750710.0, "p25": 12}, "type": "Feature"}, {"geometry": {"coordinates": [-74.1361604, 4.601484], "type": "Point"}, "properties": {"timestamp": 1552750715.0, "p25": 12}, "type": "Feature"}, {"geometry": {"coordinates": [-74.1361604, 4.601484], "type": "Point"}, "properties": {"timestamp": 1552750720.0, "p25": 12}, "type": "Feature"}, {"geometry": {"coordinates": [-74.1361832, 4.6014963], "type": "Point"}, "properties": {"timestamp": 1552750725.0, "p25": 12}, "type": "Feature"}, {"geometry": {"coordinates": [-74.1361832, 4.6014963], "type": "Point"}, "properties": {"timestamp": 1552750730.0, "p25": 12}, "type": "Feature"}, {"geometry": {"coordinates": [-74.1362514, 4.6015758], "type": "Point"}, "properties": {"timestamp": 1552750735.0, "p25": 12}, "type": "Feature"}, {"geometry": {"coordinates": [-74.1362514, 4.6015758], "type": "Point"}, "properties": {"timestamp": 1552750741.0, "p25": 13}, "type": "Feature"}, {"geometry": {"coordinates": [-74.1362575, 4.6016458], "type": "Point"}, "properties": {"timestamp": 1552750746.0, "p25": 13}, "type": "Feature"}, {"geometry": {"coordinates": [-74.1362575, 4.6016458], "type": "Point"}, "properties": {"timestamp": 1552750751.0, "p25": 15}, "type": "Feature"}, {"geometry": {"coordinates": [-74.1362262, 4.6017166], "type": "Point"}, "properties": {"timestamp": 1552750756.0, "p25": 17}, "type": "Feature"}, {"geometry": {"coordinates": [-74.1362262, 4.6017166], "type": "Point"}, "properties": {"timestamp": 1552750761.0, "p25": 19}, "type": "Feature"}, {"geometry": {"coordinates": [-74.1362035, 4.6017575], "type": "Point"}, "properties": {"timestamp": 1552750766.0, "p25": 20}, "type": "Feature"}, {"geometry": {"coordinates": [-74.1362035, 4.6017575], "type": "Point"}, "properties": {"timestamp": 1552750771.0, "p25": 18}, "type": "Feature"}, {"geometry": {"coordinates": [-74.1361725, 4.6018072], "type": "Point"}, "properties": {"timestamp": 1552750776.0, "p25": 13}, "type": "Feature"}, {"geometry": {"coordinates": [-74.1361725, 4.6018072], "type": "Point"}, "properties": {"timestamp": 1552750781.0, "p25": 11}, "type": "Feature"}, {"geometry": {"coordinates": [-74.1361552, 4.6018288], "type": "Point"}, "properties": {"timestamp": 1552750787.0, "p25": 10}, "type": "Feature"}, {"geometry": {"coordinates": [-74.1361552, 4.6018288], "type": "Point"}, "properties": {"timestamp": 1552750792.0, "p25": 10}, "type": "Feature"}, {"geometry": {"coordinates": [-74.1362325, 4.6020424], "type": "Point"}, "properties": {"timestamp": 1552750797.0, "p25": 11}, "type": "Feature"}, {"geometry": {"coordinates": [-74.1362325, 4.6020424], "type": "Point"}, "properties": {"timestamp": 1552750802.0, "p25": 12}, "type": "Feature"}, {"geometry": {"coordinates": [-74.1362369, 4.6020785], "type": "Point"}, "properties": {"timestamp": 1552750807.0, "p25": 12}, "type": "Feature"}, {"geometry": {"coordinates": [-74.1362369, 4.6020785], "type": "Point"}, "properties": {"timestamp": 1552750812.0, "p25": 14}, "type": "Feature"}, {"geometry": {"coordinates": [-74.1363239, 4.6021441], "type": "Point"}, "properties": {"timestamp": 1552750817.0, "p25": 18}, "type": "Feature"}, {"geometry": {"coordinates": [-74.1363239, 4.6021441], "type": "Point"}, "properties": {"timestamp": 1552750822.0, "p25": 21}, "type": "Feature"}, {"geometry": {"coordinates": [-74.1363995, 4.6020696], "type": "Point"}, "properties": {"timestamp": 1552750827.0, "p25": 17}, "type": "Feature"}, {"geometry": {"coordinates": [-74.1363995, 4.6020696], "type": "Point"}, "properties": {"timestamp": 1552750833.0, "p25": 12}, "type": "Feature"}, {"geometry": {"coordinates": [-74.136492, 4.6020159], "type": "Point"}, "properties": {"timestamp": 1552750838.0, "p25": 10}, "type": "Feature"}, {"geometry": {"coordinates": [-74.136492, 4.6020159], "type": "Point"}, "properties": {"timestamp": 1552750843.0, "p25": 11}, "type": "Feature"}, {"geometry": {"coordinates": [-74.1365547, 4.6019059], "type": "Point"}, "properties": {"timestamp": 1552750848.0, "p25": 11}, "type": "Feature"}, {"geometry": {"coordinates": [-74.1365547, 4.6019059], "type": "Point"}, "properties": {"timestamp": 1552750853.0, "p25": 11}, "type": "Feature"}, {"geometry": {"coordinates": [-74.1365892, 4.6018617], "type": "Point"}, "properties": {"timestamp": 1552750858.0, "p25": 10}, "type": "Feature"}, {"geometry": {"coordinates": [-74.1365892, 4.6018617], "type": "Point"}, "properties": {"timestamp": 1552750863.0, "p25": 11}, "type": "Feature"}, {"geometry": {"coordinates": [-74.1365867, 4.6018546], "type": "Point"}, "properties": {"timestamp": 1552750868.0, "p25": 15}, "type": "Feature"}, {"geometry": {"coordinates": [-74.1365867, 4.6018546], "type": "Point"}, "properties": {"timestamp": 1552750873.0, "p25": 16}, "type": "Feature"}, {"geometry": {"coordinates": [-74.1367233, 4.6019788], "type": "Point"}, "properties": {"timestamp": 1552750879.0, "p25": 15}, "type": "Feature"}, {"geometry": {"coordinates": [-74.1367233, 4.6019788], "type": "Point"}, "properties": {"timestamp": 1552750884.0, "p25": 15}, "type": "Feature"}, {"geometry": {"coordinates": [-74.1368256, 4.6020702], "type": "Point"}, "properties": {"timestamp": 1552750889.0, "p25": 15}, "type": "Feature"}, {"geometry": {"coordinates": [-74.1368256, 4.6020702], "type": "Point"}, "properties": {"timestamp": 1552750894.0, "p25": 13}, "type": "Feature"}, {"geometry": {"coordinates": [-74.1369259, 4.6021492], "type": "Point"}, "properties": {"timestamp": 1552750899.0, "p25": 12}, "type": "Feature"}, {"geometry": {"coordinates": [-74.1369259, 4.6021492], "type": "Point"}, "properties": {"timestamp": 1552750904.0, "p25": 11}, "type": "Feature"}, {"geometry": {"coordinates": [-74.1369486, 4.602183], "type": "Point"}, "properties": {"timestamp": 1552750909.0, "p25": 11}, "type": "Feature"}, {"geometry": {"coordinates": [-74.1369486, 4.602183], "type": "Point"}, "properties": {"timestamp": 1552750914.0, "p25": 11}, "type": "Feature"}, {"geometry": {"coordinates": [-74.1370559, 4.6022471], "type": "Point"}, "properties": {"timestamp": 1552750919.0, "p25": 11}, "type": "Feature"}, {"geometry": {"coordinates": [-74.1370559, 4.6022471], "type": "Point"}, "properties": {"timestamp": 1552750925.0, "p25": 11}, "type": "Feature"}, {"geometry": {"coordinates": [-74.137152, 4.602295], "type": "Point"}, "properties": {"timestamp": 1552750930.0, "p25": 11}, "type": "Feature"}, {"geometry": {"coordinates": [-74.137152, 4.602295], "type": "Point"}, "properties": {"timestamp": 1552750935.0, "p25": 11}, "type": "Feature"}, {"geometry": {"coordinates": [-74.1372071, 4.6023548], "type": "Point"}, "properties": {"timestamp": 1552750940.0, "p25": 15}, "type": "Feature"}, {"geometry": {"coordinates": [-74.1372071, 4.6023548], "type": "Point"}, "properties": {"timestamp": 1552750945.0, "p25": 19}, "type": "Feature"}, {"geometry": {"coordinates": [-74.1371956, 4.6023614], "type": "Point"}, "properties": {"timestamp": 1552750950.0, "p25": 20}, "type": "Feature"}, {"geometry": {"coordinates": [-74.1371956, 4.6023614], "type": "Point"}, "properties": {"timestamp": 1552750955.0, "p25": 20}, "type": "Feature"}, {"geometry": {"coordinates": [-74.1370846, 4.6025153], "type": "Point"}, "properties": {"timestamp": 1552750960.0, "p25": 27}, "type": "Feature"}, {"geometry": {"coordinates": [-74.1370845, 4.6025255], "type": "Point"}, "properties": {"timestamp": 1552750965.0, "p25": 36}, "type": "Feature"}, {"geometry": {"coordinates": [-74.1370226, 4.6025757], "type": "Point"}, "properties": {"timestamp": 1552750971.0, "p25": 54}, "type": "Feature"}, {"geometry": {"coordinates": [-74.1370226, 4.6025757], "type": "Point"}, "properties": {"timestamp": 1552750976.0, "p25": 92}, "type": "Feature"}, {"geometry": {"coordinates": [-74.1369929, 4.602665], "type": "Point"}, "properties": {"timestamp": 1552750981.0, "p25": 138}, "type": "Feature"}, {"geometry": {"coordinates": [-74.1369929, 4.602665], "type": "Point"}, "properties": {"timestamp": 1552750986.0, "p25": 169}, "type": "Feature"}, {"geometry": {"coordinates": [-74.1369709, 4.6027064], "type": "Point"}, "properties": {"timestamp": 1552750991.0, "p25": 172}, "type": "Feature"}, {"geometry": {"coordinates": [-74.1369709, 4.6027064], "type": "Point"}, "properties": {"timestamp": 1552750996.0, "p25": 129}, "type": "Feature"}, {"geometry": {"coordinates": [-74.1368756, 4.602825], "type": "Point"}, "properties": {"timestamp": 1552751001.0, "p25": 85}, "type": "Feature"}, {"geometry": {"coordinates": [-74.1368756, 4.602825], "type": "Point"}, "properties": {"timestamp": 1552751006.0, "p25": 59}, "type": "Feature"}, {"geometry": {"coordinates": [-74.1368293, 4.6028946], "type": "Point"}, "properties": {"timestamp": 1552751011.0, "p25": 38}, "type": "Feature"}, {"geometry": {"coordinates": [-74.1368293, 4.6028946], "type": "Point"}, "properties": {"timestamp": 1552751017.0, "p25": 23}, "type": "Feature"}, {"geometry": {"coordinates": [-74.1367632, 4.6029116], "type": "Point"}, "properties": {"timestamp": 1552751022.0, "p25": 19}, "type": "Feature"}, {"geometry": {"coordinates": [-74.1367632, 4.6029116], "type": "Point"}, "properties": {"timestamp": 1552751027.0, "p25": 24}, "type": "Feature"}, {"geometry": {"coordinates": [-74.1367268, 4.6029879], "type": "Point"}, "properties": {"timestamp": 1552751032.0, "p25": 34}, "type": "Feature"}, {"geometry": {"coordinates": [-74.1367268, 4.6029879], "type": "Point"}, "properties": {"timestamp": 1552751037.0, "p25": 39}, "type": "Feature"}, {"geometry": {"coordinates": [-74.1366646, 4.6030741], "type": "Point"}, "properties": {"timestamp": 1552751042.0, "p25": 30}, "type": "Feature"}, {"geometry": {"coordinates": [-74.1366646, 4.6030741], "type": "Point"}, "properties": {"timestamp": 1552751047.0, "p25": 18}, "type": "Feature"}, {"geometry": {"coordinates": [-74.1365891, 4.6031433], "type": "Point"}, "properties": {"timestamp": 1552751052.0, "p25": 15}, "type": "Feature"}, {"geometry": {"coordinates": [-74.1365891, 4.6031433], "type": "Point"}, "properties": {"timestamp": 1552751057.0, "p25": 14}, "type": "Feature"}, {"geometry": {"coordinates": [-74.1365185, 4.6032556], "type": "Point"}, "properties": {"timestamp": 1552751063.0, "p25": 14}, "type": "Feature"}, {"geometry": {"coordinates": [-74.1365018, 4.6032887], "type": "Point"}, "properties": {"timestamp": 1552751068.0, "p25": 16}, "type": "Feature"}, {"geometry": {"coordinates": [-74.1365018, 4.6032887], "type": "Point"}, "properties": {"timestamp": 1552751073.0, "p25": 15}, "type": "Feature"}, {"geometry": {"coordinates": [-74.1364875, 4.603307], "type": "Point"}, "properties": {"timestamp": 1552751078.0, "p25": 13}, "type": "Feature"}, {"geometry": {"coordinates": [-74.1364875, 4.603307], "type": "Point"}, "properties": {"timestamp": 1552751083.0, "p25": 12}, "type": "Feature"}, {"geometry": {"coordinates": [-74.1364584, 4.6033604], "type": "Point"}, "properties": {"timestamp": 1552751088.0, "p25": 12}, "type": "Feature"}, {"geometry": {"coordinates": [-74.1364584, 4.6033604], "type": "Point"}, "properties": {"timestamp": 1552751093.0, "p25": 12}, "type": "Feature"}, {"geometry": {"coordinates": [-74.1364338, 4.603432], "type": "Point"}, "properties": {"timestamp": 1552751098.0, "p25": 12}, "type": "Feature"}, {"geometry": {"coordinates": [-74.1364338, 4.603432], "type": "Point"}, "properties": {"timestamp": 1552751103.0, "p25": 12}, "type": "Feature"}, {"geometry": {"coordinates": [-74.1363163, 4.603606], "type": "Point"}, "properties": {"timestamp": 1552751109.0, "p25": 12}, "type": "Feature"}, {"geometry": {"coordinates": [-74.1363163, 4.603606], "type": "Point"}, "properties": {"timestamp": 1552751114.0, "p25": 12}, "type": "Feature"}, {"geometry": {"coordinates": [-74.1362734, 4.6036573], "type": "Point"}, "properties": {"timestamp": 1552751119.0, "p25": 13}, "type": "Feature"}, {"geometry": {"coordinates": [-74.1362734, 4.6036573], "type": "Point"}, "properties": {"timestamp": 1552751124.0, "p25": 13}, "type": "Feature"}, {"geometry": {"coordinates": [-74.1362233, 4.6037222], "type": "Point"}, "properties": {"timestamp": 1552751129.0, "p25": 12}, "type": "Feature"}, {"geometry": {"coordinates": [-74.1362233, 4.6037222], "type": "Point"}, "properties": {"timestamp": 1552751134.0, "p25": 12}, "type": "Feature"}, {"geometry": {"coordinates": [-74.1361478, 4.6038153], "type": "Point"}, "properties": {"timestamp": 1552751139.0, "p25": 12}, "type": "Feature"}, {"geometry": {"coordinates": [-74.1361478, 4.6038153], "type": "Point"}, "properties": {"timestamp": 1552751144.0, "p25": 12}, "type": "Feature"}, {"geometry": {"coordinates": [-74.1361478, 4.6038153], "type": "Point"}, "properties": {"timestamp": 1552751149.0, "p25": 12}, "type": "Feature"}, {"geometry": {"coordinates": [-74.136072, 4.6039077], "type": "Point"}, "properties": {"timestamp": 1552751155.0, "p25": 13}, "type": "Feature"}, {"geometry": {"coordinates": [-74.136072, 4.6039077], "type": "Point"}, "properties": {"timestamp": 1552751160.0, "p25": 13}, "type": "Feature"}, {"geometry": {"coordinates": [-74.1360421, 4.6039392], "type": "Point"}, "properties": {"timestamp": 1552751165.0, "p25": 13}, "type": "Feature"}, {"geometry": {"coordinates": [-74.1360421, 4.6039392], "type": "Point"}, "properties": {"timestamp": 1552751170.0, "p25": 14}, "type": "Feature"}, {"geometry": {"coordinates": [-74.1360404, 4.6039431], "type": "Point"}, "properties": {"timestamp": 1552751175.0, "p25": 16}, "type": "Feature"}, {"geometry": {"coordinates": [-74.1360315, 4.6039485], "type": "Point"}, "properties": {"timestamp": 1552751180.0, "p25": 15}, "type": "Feature"}, {"geometry": {"coordinates": [-74.1360315, 4.6039485], "type": "Point"}, "properties": {"timestamp": 1552751185.0, "p25": 14}, "type": "Feature"}, {"geometry": {"coordinates": [-74.1360377, 4.6039471], "type": "Point"}, "properties": {"timestamp": 1552751190.0, "p25": 14}, "type": "Feature"}, {"geometry": {"coordinates": [-74.1360377, 4.6039471], "type": "Point"}, "properties": {"timestamp": 1552751196.0, "p25": 14}, "type": "Feature"}, {"geometry": {"coordinates": [-74.1360602, 4.6039168], "type": "Point"}, "properties": {"timestamp": 1552751201.0, "p25": 14}, "type": "Feature"}, {"geometry": {"coordinates": [-74.1360602, 4.6039168], "type": "Point"}, "properties": {"timestamp": 1552751206.0, "p25": 13}, "type": "Feature"}, {"geometry": {"coordinates": [-74.1361618, 4.603819], "type": "Point"}, "properties": {"timestamp": 1552751211.0, "p25": 11}, "type": "Feature"}, {"geometry": {"coordinates": [-74.1361618, 4.603819], "type": "Point"}, "properties": {"timestamp": 1552751216.0, "p25": 11}, "type": "Feature"}, {"geometry": {"coordinates": [-74.1362403, 4.6037492], "type": "Point"}, "properties": {"timestamp": 1552751221.0, "p25": 11}, "type": "Feature"}, {"geometry": {"coordinates": [-74.1362403, 4.6037492], "type": "Point"}, "properties": {"timestamp": 1552751226.0, "p25": 11}, "type": "Feature"}, {"geometry": {"coordinates": [-74.1362926, 4.6036901], "type": "Point"}, "properties": {"timestamp": 1552751231.0, "p25": 11}, "type": "Feature"}, {"geometry": {"coordinates": [-74.1362926, 4.6036901], "type": "Point"}, "properties": {"timestamp": 1552751236.0, "p25": 12}, "type": "Feature"}, {"geometry": {"coordinates": [-74.1363352, 4.6036518], "type": "Point"}, "properties": {"timestamp": 1552751242.0, "p25": 13}, "type": "Feature"}, {"geometry": {"coordinates": [-74.1363352, 4.6036518], "type": "Point"}, "properties": {"timestamp": 1552751247.0, "p25": 13}, "type": "Feature"}, {"geometry": {"coordinates": [-74.1363403, 4.6035597], "type": "Point"}, "properties": {"timestamp": 1552751252.0, "p25": 13}, "type": "Feature"}, {"geometry": {"coordinates": [-74.1363403, 4.6035597], "type": "Point"}, "properties": {"timestamp": 1552751257.0, "p25": 11}, "type": "Feature"}, {"geometry": {"coordinates": [-74.136368, 4.6035064], "type": "Point"}, "properties": {"timestamp": 1552751262.0, "p25": 11}, "type": "Feature"}, {"geometry": {"coordinates": [-74.136368, 4.6035064], "type": "Point"}, "properties": {"timestamp": 1552751267.0, "p25": 12}, "type": "Feature"}, {"geometry": {"coordinates": [-74.136446, 4.6033965], "type": "Point"}, "properties": {"timestamp": 1552751272.0, "p25": 13}, "type": "Feature"}, {"geometry": {"coordinates": [-74.136446, 4.6033965], "type": "Point"}, "properties": {"timestamp": 1552751277.0, "p25": 13}, "type": "Feature"}, {"geometry": {"coordinates": [-74.1364927, 4.6033299], "type": "Point"}, "properties": {"timestamp": 1552751282.0, "p25": 12}, "type": "Feature"}, {"geometry": {"coordinates": [-74.1364927, 4.6033299], "type": "Point"}, "properties": {"timestamp": 1552751288.0, "p25": 11}, "type": "Feature"}, {"geometry": {"coordinates": [-74.136531, 4.6032667], "type": "Point"}, "properties": {"timestamp": 1552751293.0, "p25": 10}, "type": "Feature"}, {"geometry": {"coordinates": [-74.136531, 4.6032667], "type": "Point"}, "properties": {"timestamp": 1552751298.0, "p25": 12}, "type": "Feature"}, {"geometry": {"coordinates": [-74.1365855, 4.6031941], "type": "Point"}, "properties": {"timestamp": 1552751303.0, "p25": 13}, "type": "Feature"}, {"geometry": {"coordinates": [-74.1366842, 4.6030816], "type": "Point"}, "properties": {"timestamp": 1552751308.0, "p25": 12}, "type": "Feature"}, {"geometry": {"coordinates": [-74.1366842, 4.6030816], "type": "Point"}, "properties": {"timestamp": 1552751313.0, "p25": 12}, "type": "Feature"}, {"geometry": {"coordinates": [-74.1367494, 4.6030066], "type": "Point"}, "properties": {"timestamp": 1552751318.0, "p25": 12}, "type": "Feature"}, {"geometry": {"coordinates": [-74.1367494, 4.6030066], "type": "Point"}, "properties": {"timestamp": 1552751323.0, "p25": 12}, "type": "Feature"}, {"geometry": {"coordinates": [-74.1368755, 4.6029283], "type": "Point"}, "properties": {"timestamp": 1552751328.0, "p25": 12}, "type": "Feature"}, {"geometry": {"coordinates": [-74.1368755, 4.6029283], "type": "Point"}, "properties": {"timestamp": 1552751334.0, "p25": 12}, "type": "Feature"}, {"geometry": {"coordinates": [-74.1368638, 4.602872], "type": "Point"}, "properties": {"timestamp": 1552751339.0, "p25": 11}, "type": "Feature"}, {"geometry": {"coordinates": [-74.1368638, 4.602872], "type": "Point"}, "properties": {"timestamp": 1552751344.0, "p25": 12}, "type": "Feature"}, {"geometry": {"coordinates": [-74.1368638, 4.602872], "type": "Point"}, "properties": {"timestamp": 1552751349.0, "p25": 15}, "type": "Feature"}, {"geometry": {"coordinates": [-74.1368905, 4.602826], "type": "Point"}, "properties": {"timestamp": 1552751354.0, "p25": 17}, "type": "Feature"}, {"geometry": {"coordinates": [-74.1368905, 4.602826], "type": "Point"}, "properties": {"timestamp": 1552751359.0, "p25": 18}, "type": "Feature"}, {"geometry": {"coordinates": [-74.1369639, 4.6027331], "type": "Point"}, "properties": {"timestamp": 1552751364.0, "p25": 24}, "type": "Feature"}, {"geometry": {"coordinates": [-74.1369639, 4.6027331], "type": "Point"}, "properties": {"timestamp": 1552751369.0, "p25": 40}, "type": "Feature"}, {"geometry": {"coordinates": [-74.1370279, 4.6026401], "type": "Point"}, "properties": {"timestamp": 1552751374.0, "p25": 69}, "type": "Feature"}, {"geometry": {"coordinates": [-74.1370279, 4.6026401], "type": "Point"}, "properties": {"timestamp": 1552751380.0, "p25": 78}, "type": "Feature"}, {"geometry": {"coordinates": [-74.1370523, 4.6026007], "type": "Point"}, "properties": {"timestamp": 1552751385.0, "p25": 57}, "type": "Feature"}, {"geometry": {"coordinates": [-74.1370523, 4.6026007], "type": "Point"}, "properties": {"timestamp": 1552751390.0, "p25": 40}, "type": "Feature"}, {"geometry": {"coordinates": [-74.1371171, 4.6024873], "type": "Point"}, "properties": {"timestamp": 1552751395.0, "p25": 35}, "type": "Feature"}, {"geometry": {"coordinates": [-74.1371171, 4.6024873], "type": "Point"}, "properties": {"timestamp": 1552751400.0, "p25": 24}, "type": "Feature"}, {"geometry": {"coordinates": [-74.1371186, 4.6023901], "type": "Point"}, "properties": {"timestamp": 1552751405.0, "p25": 14}, "type": "Feature"}, {"geometry": {"coordinates": [-74.1371186, 4.6023901], "type": "Point"}, "properties": {"timestamp": 1552751410.0, "p25": 12}, "type": "Feature"}, {"geometry": {"coordinates": [-74.1373543, 4.6021871], "type": "Point"}, "properties": {"timestamp": 1552751415.0, "p25": 12}, "type": "Feature"}, {"geometry": {"coordinates": [-74.1373066, 4.602167], "type": "Point"}, "properties": {"timestamp": 1552751420.0, "p25": 15}, "type": "Feature"}, {"geometry": {"coordinates": [-74.1373066, 4.602167], "type": "Point"}, "properties": {"timestamp": 1552751426.0, "p25": 19}, "type": "Feature"}, {"geometry": {"coordinates": [-74.1373393, 4.6021558], "type": "Point"}, "properties": {"timestamp": 1552751431.0, "p25": 21}, "type": "Feature"}, {"geometry": {"coordinates": [-74.1373393, 4.6021558], "type": "Point"}, "properties": {"timestamp": 1552751436.0, "p25": 24}, "type": "Feature"}, {"geometry": {"coordinates": [-74.137398, 4.6021527], "type": "Point"}, "properties": {"timestamp": 1552751441.0, "p25": 24}, "type": "Feature"}, {"geometry": {"coordinates": [-74.137398, 4.6021527], "type": "Point"}, "properties": {"timestamp": 1552751446.0, "p25": 22}, "type": "Feature"}, {"geometry": {"coordinates": [-74.1373718, 4.6021401], "type": "Point"}, "properties": {"timestamp": 1552751451.0, "p25": 21}, "type": "Feature"}, {"geometry": {"coordinates": [-74.1373718, 4.6021401], "type": "Point"}, "properties": {"timestamp": 1552751456.0, "p25": 21}, "type": "Feature"}, {"geometry": {"coordinates": [-74.137399, 4.6021488], "type": "Point"}, "properties": {"timestamp": 1552751461.0, "p25": 21}, "type": "Feature"}, {"geometry": {"coordinates": [-74.137399, 4.6021488], "type": "Point"}, "properties": {"timestamp": 1552751466.0, "p25": 21}, "type": "Feature"}, {"geometry": {"coordinates": [-74.1374047, 4.6021594], "type": "Point"}, "properties": {"timestamp": 1552751472.0, "p25": 20}, "type": "Feature"}, {"geometry": {"coordinates": [-74.1374047, 4.6021594], "type": "Point"}, "properties": {"timestamp": 1552751477.0, "p25": 18}, "type": "Feature"}, {"geometry": {"coordinates": [-74.1374195, 4.6021344], "type": "Point"}, "properties": {"timestamp": 1552751482.0, "p25": 16}, "type": "Feature"}, {"geometry": {"coordinates": [-74.1374195, 4.6021344], "type": "Point"}, "properties": {"timestamp": 1552751487.0, "p25": 16}, "type": "Feature"}, {"geometry": {"coordinates": [-74.1374231, 4.6021172], "type": "Point"}, "properties": {"timestamp": 1552751492.0, "p25": 16}, "type": "Feature"}, {"geometry": {"coordinates": [-74.1374231, 4.6021172], "type": "Point"}, "properties": {"timestamp": 1552751497.0, "p25": 15}, "type": "Feature"}, {"geometry": {"coordinates": [-74.1374965, 4.6020388], "type": "Point"}, "properties": {"timestamp": 1552751502.0, "p25": 13}, "type": "Feature"}, {"geometry": {"coordinates": [-74.1374965, 4.6020388], "type": "Point"}, "properties": {"timestamp": 1552751507.0, "p25": 13}, "type": "Feature"}, {"geometry": {"coordinates": [-74.1374936, 4.6019934], "type": "Point"}, "properties": {"timestamp": 1552751512.0, "p25": 15}, "type": "Feature"}, {"geometry": {"coordinates": [-74.1374936, 4.6019934], "type": "Point"}, "properties": {"timestamp": 1552751518.0, "p25": 17}, "type": "Feature"}, {"geometry": {"coordinates": [-74.1375493, 4.601913], "type": "Point"}, "properties": {"timestamp": 1552751523.0, "p25": 16}, "type": "Feature"}, {"geometry": {"coordinates": [-74.1375493, 4.601913], "type": "Point"}, "properties": {"timestamp": 1552751528.0, "p25": 15}, "type": "Feature"}, {"geometry": {"coordinates": [-74.1375979, 4.6018449], "type": "Point"}, "properties": {"timestamp": 1552751533.0, "p25": 17}, "type": "Feature"}, {"geometry": {"coordinates": [-74.1375979, 4.6018449], "type": "Point"}, "properties": {"timestamp": 1552751538.0, "p25": 20}, "type": "Feature"}, {"geometry": {"coordinates": [-74.1376461, 4.6017799], "type": "Point"}, "properties": {"timestamp": 1552751543.0, "p25": 26}, "type": "Feature"}, {"geometry": {"coordinates": [-74.1376461, 4.6017799], "type": "Point"}, "properties": {"timestamp": 1552751548.0, "p25": 39}, "type": "Feature"}, {"geometry": {"coordinates": [-74.1377124, 4.6017229], "type": "Point"}, "properties": {"timestamp": 1552751553.0, "p25": 45}, "type": "Feature"}, {"geometry": {"coordinates": [-74.1377124, 4.6017229], "type": "Point"}, "properties": {"timestamp": 1552751558.0, "p25": 37}, "type": "Feature"}, {"geometry": {"coordinates": [-74.1377677, 4.6017363], "type": "Point"}, "properties": {"timestamp": 1552751564.0, "p25": 32}, "type": "Feature"}, {"geometry": {"coordinates": [-74.1377677, 4.6017363], "type": "Point"}, "properties": {"timestamp": 1552751569.0, "p25": 34}, "type": "Feature"}, {"geometry": {"coordinates": [-74.1378478, 4.6017706], "type": "Point"}, "properties": {"timestamp": 1552751574.0, "p25": 37}, "type": "Feature"}, {"geometry": {"coordinates": [-74.1378478, 4.6017706], "type": "Point"}, "properties": {"timestamp": 1552751579.0, "p25": 38}, "type": "Feature"}, {"geometry": {"coordinates": [-74.1379568, 4.601823], "type": "Point"}, "properties": {"timestamp": 1552751584.0, "p25": 33}, "type": "Feature"}, {"geometry": {"coordinates": [-74.1379568, 4.601823], "type": "Point"}, "properties": {"timestamp": 1552751589.0, "p25": 27}, "type": "Feature"}, {"geometry": {"coordinates": [-74.1380052, 4.6018532], "type": "Point"}, "properties": {"timestamp": 1552751594.0, "p25": 25}, "type": "Feature"}, {"geometry": {"coordinates": [-74.1380052, 4.6018532], "type": "Point"}, "properties": {"timestamp": 1552751599.0, "p25": 24}, "type": "Feature"}, {"geometry": {"coordinates": [-74.1380169, 4.6018668], "type": "Point"}, "properties": {"timestamp": 1552751604.0, "p25": 20}, "type": "Feature"}, {"geometry": {"coordinates": [-74.1380169, 4.6018668], "type": "Point"}, "properties": {"timestamp": 1552751610.0, "p25": 16}, "type": "Feature"}, {"geometry": {"coordinates": [-74.1380192, 4.6018636], "type": "Point"}, "properties": {"timestamp": 1552751615.0, "p25": 15}, "type": "Feature"}, {"geometry": {"coordinates": [-74.1380192, 4.6018636], "type": "Point"}, "properties": {"timestamp": 1552751620.0, "p25": 15}, "type": "Feature"}, {"geometry": {"coordinates": [-74.1380234, 4.6018658], "type": "Point"}, "properties": {"timestamp": 1552751625.0, "p25": 14}, "type": "Feature"}, {"geometry": {"coordinates": [-74.1380234, 4.6018658], "type": "Point"}, "properties": {"timestamp": 1552751630.0, "p25": 14}, "type": "Feature"}, {"geometry": {"coordinates": [-74.1380397, 4.6018674], "type": "Point"}, "properties": {"timestamp": 1552751635.0, "p25": 16}, "type": "Feature"}, {"geometry": {"coordinates": [-74.1380397, 4.6018674], "type": "Point"}, "properties": {"timestamp": 1552751640.0, "p25": 16}, "type": "Feature"}, {"geometry": {"coordinates": [-74.1380258, 4.6018674], "type": "Point"}, "properties": {"timestamp": 1552751645.0, "p25": 17}, "type": "Feature"}, {"geometry": {"coordinates": [-74.1380258, 4.6018674], "type": "Point"}, "properties": {"timestamp": 1552751650.0, "p25": 19}, "type": "Feature"}, {"geometry": {"coordinates": [-74.1380161, 4.6018505], "type": "Point"}, "properties": {"timestamp": 1552751656.0, "p25": 19}, "type": "Feature"}, {"geometry": {"coordinates": [-74.1380161, 4.6018505], "type": "Point"}, "properties": {"timestamp": 1552751661.0, "p25": 17}, "type": "Feature"}, {"geometry": {"coordinates": [-74.1380222, 4.6018622], "type": "Point"}, "properties": {"timestamp": 1552751666.0, "p25": 15}, "type": "Feature"}, {"geometry": {"coordinates": [-74.1380222, 4.6018622], "type": "Point"}, "properties": {"timestamp": 1552751671.0, "p25": 14}, "type": "Feature"}, {"geometry": {"coordinates": [-74.1380635, 4.6019307], "type": "Point"}, "properties": {"timestamp": 1552751676.0, "p25": 14}, "type": "Feature"}, {"geometry": {"coordinates": [-74.1380635, 4.6019307], "type": "Point"}, "properties": {"timestamp": 1552751681.0, "p25": 14}, "type": "Feature"}, {"geometry": {"coordinates": [-74.138061, 4.6019414], "type": "Point"}, "properties": {"timestamp": 1552751686.0, "p25": 13}, "type": "Feature"}, {"geometry": {"coordinates": [-74.138061, 4.6019414], "type": "Point"}, "properties": {"timestamp": 1552751691.0, "p25": 13}, "type": "Feature"}, {"geometry": {"coordinates": [-74.1380694, 4.6019412], "type": "Point"}, "properties": {"timestamp": 1552751696.0, "p25": 13}, "type": "Feature"}, {"geometry": {"coordinates": [-74.1380694, 4.6019412], "type": "Point"}, "properties": {"timestamp": 1552751702.0, "p25": 13}, "type": "Feature"}, {"geometry": {"coordinates": [-74.138058, 4.6019318], "type": "Point"}, "properties": {"timestamp": 1552751707.0, "p25": 13}, "type": "Feature"}, {"geometry": {"coordinates": [-74.138058, 4.6019318], "type": "Point"}, "properties": {"timestamp": 1552751712.0, "p25": 14}, "type": "Feature"}, {"geometry": {"coordinates": [-74.138052, 4.6019224], "type": "Point"}, "properties": {"timestamp": 1552751717.0, "p25": 13}, "type": "Feature"}, {"geometry": {"coordinates": [-74.138052, 4.6019224], "type": "Point"}, "properties": {"timestamp": 1552751722.0, "p25": 12}, "type": "Feature"}, {"geometry": {"coordinates": [-74.1380548, 4.6019324], "type": "Point"}, "properties": {"timestamp": 1552751727.0, "p25": 13}, "type": "Feature"}, {"geometry": {"coordinates": [-74.1380548, 4.6019324], "type": "Point"}, "properties": {"timestamp": 1552751732.0, "p25": 14}, "type": "Feature"}, {"geometry": {"coordinates": [-74.1380693, 4.6019316], "type": "Point"}, "properties": {"timestamp": 1552751737.0, "p25": 13}, "type": "Feature"}, {"geometry": {"coordinates": [-74.1380693, 4.6019316], "type": "Point"}, "properties": {"timestamp": 1552751742.0, "p25": 13}, "type": "Feature"}, {"geometry": {"coordinates": [-74.1380693, 4.6019316], "type": "Point"}, "properties": {"timestamp": 1552751748.0, "p25": 13}, "type": "Feature"}, {"geometry": {"coordinates": [-74.1380763, 4.6019322], "type": "Point"}, "properties": {"timestamp": 1552751753.0, "p25": 13}, "type": "Feature"}, {"geometry": {"coordinates": [-74.1380763, 4.6019322], "type": "Point"}, "properties": {"timestamp": 1552751758.0, "p25": 13}, "type": "Feature"}, {"geometry": {"coordinates": [-74.1380842, 4.6019155], "type": "Point"}, "properties": {"timestamp": 1552751763.0, "p25": 13}, "type": "Feature"}, {"geometry": {"coordinates": [-74.1380842, 4.6019155], "type": "Point"}, "properties": {"timestamp": 1552751768.0, "p25": 12}, "type": "Feature"}, {"geometry": {"coordinates": [-74.1380741, 4.6019554], "type": "Point"}, "properties": {"timestamp": 1552751773.0, "p25": 12}, "type": "Feature"}, {"geometry": {"coordinates": [-74.1380741, 4.6019554], "type": "Point"}, "properties": {"timestamp": 1552751778.0, "p25": 15}, "type": "Feature"}, {"geometry": {"coordinates": [-74.1380839, 4.6019716], "type": "Point"}, "properties": {"timestamp": 1552751783.0, "p25": 17}, "type": "Feature"}, {"geometry": {"coordinates": [-74.1380839, 4.6019716], "type": "Point"}, "properties": {"timestamp": 1552751788.0, "p25": 16}, "type": "Feature"}, {"geometry": {"coordinates": [-74.1380727, 4.6019739], "type": "Point"}, "properties": {"timestamp": 1552751794.0, "p25": 16}, "type": "Feature"}, {"geometry": {"coordinates": [-74.1380727, 4.6019739], "type": "Point"}, "properties": {"timestamp": 1552751799.0, "p25": 17}, "type": "Feature"}, {"geometry": {"coordinates": [-74.1381256, 4.6019922], "type": "Point"}, "properties": {"timestamp": 1552751804.0, "p25": 17}, "type": "Feature"}, {"geometry": {"coordinates": [-74.1381256, 4.6019922], "type": "Point"}, "properties": {"timestamp": 1552751809.0, "p25": 17}, "type": "Feature"}, {"geometry": {"coordinates": [-74.1381041, 4.6019697], "type": "Point"}, "properties": {"timestamp": 1552751814.0, "p25": 17}, "type": "Feature"}, {"geometry": {"coordinates": [-74.1381041, 4.6019697], "type": "Point"}, "properties": {"timestamp": 1552751819.0, "p25": 17}, "type": "Feature"}, {"geometry": {"coordinates": [-74.1380681, 4.6019511], "type": "Point"}, "properties": {"timestamp": 1552751824.0, "p25": 16}, "type": "Feature"}, {"geometry": {"coordinates": [-74.1380681, 4.6019511], "type": "Point"}, "properties": {"timestamp": 1552751829.0, "p25": 13}, "type": "Feature"}, {"geometry": {"coordinates": [-74.1380681, 4.6019511], "type": "Point"}, "properties": {"timestamp": 1552751834.0, "p25": 11}, "type": "Feature"}, {"geometry": {"coordinates": [-74.1380685, 4.6019488], "type": "Point"}, "properties": {"timestamp": 1552751840.0, "p25": 11}, "type": "Feature"}, {"geometry": {"coordinates": [-74.1380681, 4.6019639], "type": "Point"}, "properties": {"timestamp": 1552751845.0, "p25": 12}, "type": "Feature"}, {"geometry": {"coordinates": [-74.1380681, 4.6019639], "type": "Point"}, "properties": {"timestamp": 1552751850.0, "p25": 12}, "type": "Feature"}, {"geometry": {"coordinates": [-74.1380454, 4.6019315], "type": "Point"}, "properties": {"timestamp": 1552751855.0, "p25": 12}, "type": "Feature"}, {"geometry": {"coordinates": [-74.1380516, 4.6019301], "type": "Point"}, "properties": {"timestamp": 1552751860.0, "p25": 12}, "type": "Feature"}, {"geometry": {"coordinates": [-74.1380516, 4.6019301], "type": "Point"}, "properties": {"timestamp": 1552751865.0, "p25": 11}, "type": "Feature"}, {"geometry": {"coordinates": [-74.1380275, 4.6019004], "type": "Point"}, "properties": {"timestamp": 1552751870.0, "p25": 11}, "type": "Feature"}, {"geometry": {"coordinates": [-74.1380365, 4.6019056], "type": "Point"}, "properties": {"timestamp": 1552751875.0, "p25": 11}, "type": "Feature"}, {"geometry": {"coordinates": [-74.1380365, 4.6019056], "type": "Point"}, "properties": {"timestamp": 1552751880.0, "p25": 10}, "type": "Feature"}, {"geometry": {"coordinates": [-74.1380454, 4.6019166], "type": "Point"}, "properties": {"timestamp": 1552751886.0, "p25": 9}, "type": "Feature"}, {"geometry": {"coordinates": [-74.1380454, 4.6019166], "type": "Point"}, "properties": {"timestamp": 1552751891.0, "p25": 9}, "type": "Feature"}, {"geometry": {"coordinates": [-74.1380444, 4.6019443], "type": "Point"}, "properties": {"timestamp": 1552751896.0, "p25": 11}, "type": "Feature"}, {"geometry": {"coordinates": [-74.1380444, 4.6019443], "type": "Point"}, "properties": {"timestamp": 1552751901.0, "p25": 11}, "type": "Feature"}, {"geometry": {"coordinates": [-74.1380276, 4.6019067], "type": "Point"}, "properties": {"timestamp": 1552751906.0, "p25": 9}, "type": "Feature"}, {"geometry": {"coordinates": [-74.1380276, 4.6019067], "type": "Point"}, "properties": {"timestamp": 1552751911.0, "p25": 9}, "type": "Feature"}, {"geometry": {"coordinates": [-74.1380446, 4.6019276], "type": "Point"}, "properties": {"timestamp": 1552751916.0, "p25": 11}, "type": "Feature"}, {"geometry": {"coordinates": [-74.1380446, 4.6019276], "type": "Point"}, "properties": {"timestamp": 1552751921.0, "p25": 12}, "type": "Feature"}, {"geometry": {"coordinates": [-74.1380782, 4.6019501], "type": "Point"}, "properties": {"timestamp": 1552751926.0, "p25": 11}, "type": "Feature"}, {"geometry": {"coordinates": [-74.1380782, 4.6019501], "type": "Point"}, "properties": {"timestamp": 1552751932.0, "p25": 10}, "type": "Feature"}, {"geometry": {"coordinates": [-74.1380339, 4.6018502], "type": "Point"}, "properties": {"timestamp": 1552751937.0, "p25": 10}, "type": "Feature"}, {"geometry": {"coordinates": [-74.1380294, 4.6018569], "type": "Point"}, "properties": {"timestamp": 1552751942.0, "p25": 11}, "type": "Feature"}, {"geometry": {"coordinates": [-74.1380294, 4.6018569], "type": "Point"}, "properties": {"timestamp": 1552751947.0, "p25": 13}, "type": "Feature"}, {"geometry": {"coordinates": [-74.1380408, 4.6018491], "type": "Point"}, "properties": {"timestamp": 1552751952.0, "p25": 14}, "type": "Feature"}, {"geometry": {"coordinates": [-74.1380408, 4.6018491], "type": "Point"}, "properties": {"timestamp": 1552751957.0, "p25": 15}, "type": "Feature"}, {"geometry": {"coordinates": [-74.1380347, 4.6018465], "type": "Point"}, "properties": {"timestamp": 1552751962.0, "p25": 15}, "type": "Feature"}, {"geometry": {"coordinates": [-74.1380347, 4.6018465], "type": "Point"}, "properties": {"timestamp": 1552751967.0, "p25": 15}, "type": "Feature"}, {"geometry": {"coordinates": [-74.138024, 4.6018594], "type": "Point"}, "properties": {"timestamp": 1552751972.0, "p25": 15}, "type": "Feature"}, {"geometry": {"coordinates": [-74.138024, 4.6018594], "type": "Point"}, "properties": {"timestamp": 1552751978.0, "p25": 15}, "type": "Feature"}, {"geometry": {"coordinates": [-74.138024, 4.6018594], "type": "Point"}, "properties": {"timestamp": 1552751983.0, "p25": 16}, "type": "Feature"}, {"geometry": {"coordinates": [-74.1380625, 4.6018788], "type": "Point"}, "properties": {"timestamp": 1552751988.0, "p25": 16}, "type": "Feature"}, {"geometry": {"coordinates": [-74.1380625, 4.6018788], "type": "Point"}, "properties": {"timestamp": 1552751993.0, "p25": 16}, "type": "Feature"}, {"geometry": {"coordinates": [-74.1380331, 4.6018804], "type": "Point"}, "properties": {"timestamp": 1552751998.0, "p25": 16}, "type": "Feature"}, {"geometry": {"coordinates": [-74.1380331, 4.6018804], "type": "Point"}, "properties": {"timestamp": 1552752003.0, "p25": 16}, "type": "Feature"}, {"geometry": {"coordinates": [-74.138028, 4.6018682], "type": "Point"}, "properties": {"timestamp": 1552752008.0, "p25": 14}, "type": "Feature"}, {"geometry": {"coordinates": [-74.138028, 4.6018682], "type": "Point"}, "properties": {"timestamp": 1552752013.0, "p25": 14}, "type": "Feature"}, {"geometry": {"coordinates": [-74.1380275, 4.6018605], "type": "Point"}, "properties": {"timestamp": 1552752019.0, "p25": 15}, "type": "Feature"}, {"geometry": {"coordinates": [-74.1380275, 4.6018605], "type": "Point"}, "properties": {"timestamp": 1552752024.0, "p25": 14}, "type": "Feature"}, {"geometry": {"coordinates": [-74.1380201, 4.6018565], "type": "Point"}, "properties": {"timestamp": 1552752029.0, "p25": 14}, "type": "Feature"}, {"geometry": {"coordinates": [-74.1380201, 4.6018565], "type": "Point"}, "properties": {"timestamp": 1552752034.0, "p25": 14}, "type": "Feature"}, {"geometry": {"coordinates": [-74.1380246, 4.601857], "type": "Point"}, "properties": {"timestamp": 1552752039.0, "p25": 14}, "type": "Feature"}, {"geometry": {"coordinates": [-74.1380246, 4.601857], "type": "Point"}, "properties": {"timestamp": 1552752044.0, "p25": 14}, "type": "Feature"}, {"geometry": {"coordinates": [-74.1380282, 4.6018693], "type": "Point"}, "properties": {"timestamp": 1552752049.0, "p25": 13}, "type": "Feature"}, {"geometry": {"coordinates": [-74.1380282, 4.6018693], "type": "Point"}, "properties": {"timestamp": 1552752054.0, "p25": 13}, "type": "Feature"}, {"geometry": {"coordinates": [-74.1380311, 4.6018596], "type": "Point"}, "properties": {"timestamp": 1552752059.0, "p25": 14}, "type": "Feature"}, {"geometry": {"coordinates": [-74.1380273, 4.6018701], "type": "Point"}, "properties": {"timestamp": 1552752065.0, "p25": 16}, "type": "Feature"}, {"geometry": {"coordinates": [-74.1380273, 4.6018701], "type": "Point"}, "properties": {"timestamp": 1552752070.0, "p25": 17}, "type": "Feature"}, {"geometry": {"coordinates": [-74.1380355, 4.601877], "type": "Point"}, "properties": {"timestamp": 1552752075.0, "p25": 17}, "type": "Feature"}, {"geometry": {"coordinates": [-74.1380355, 4.601877], "type": "Point"}, "properties": {"timestamp": 1552752080.0, "p25": 15}, "type": "Feature"}, {"geometry": {"coordinates": [-74.1380496, 4.6019235], "type": "Point"}, "properties": {"timestamp": 1552752085.0, "p25": 13}, "type": "Feature"}, {"geometry": {"coordinates": [-74.1380496, 4.6019235], "type": "Point"}, "properties": {"timestamp": 1552752090.0, "p25": 13}, "type": "Feature"}, {"geometry": {"coordinates": [-74.1380683, 4.6019803], "type": "Point"}, "properties": {"timestamp": 1552752095.0, "p25": 13}, "type": "Feature"}, {"geometry": {"coordinates": [-74.1380683, 4.6019803], "type": "Point"}, "properties": {"timestamp": 1552752100.0, "p25": 12}, "type": "Feature"}, {"geometry": {"coordinates": [-74.1380703, 4.6019796], "type": "Point"}, "properties": {"timestamp": 1552752105.0, "p25": 11}, "type": "Feature"}, {"geometry": {"coordinates": [-74.1380703, 4.6019796], "type": "Point"}, "properties": {"timestamp": 1552752111.0, "p25": 12}, "type": "Feature"}, {"geometry": {"coordinates": [-74.1380667, 4.6019721], "type": "Point"}, "properties": {"timestamp": 1552752116.0, "p25": 13}, "type": "Feature"}, {"geometry": {"coordinates": [-74.1380667, 4.6019721], "type": "Point"}, "properties": {"timestamp": 1552752121.0, "p25": 14}, "type": "Feature"}, {"geometry": {"coordinates": [-74.1380523, 4.6019564], "type": "Point"}, "properties": {"timestamp": 1552752126.0, "p25": 13}, "type": "Feature"}, {"geometry": {"coordinates": [-74.1380523, 4.6019564], "type": "Point"}, "properties": {"timestamp": 1552752131.0, "p25": 12}, "type": "Feature"}, {"geometry": {"coordinates": [-74.1380384, 4.6019467], "type": "Point"}, "properties": {"timestamp": 1552752136.0, "p25": 10}, "type": "Feature"}, {"geometry": {"coordinates": [-74.1380384, 4.6019467], "type": "Point"}, "properties": {"timestamp": 1552752141.0, "p25": 10}, "type": "Feature"}, {"geometry": {"coordinates": [-74.1380395, 4.6019378], "type": "Point"}, "properties": {"timestamp": 1552752146.0, "p25": 10}, "type": "Feature"}, {"geometry": {"coordinates": [-74.1380395, 4.6019378], "type": "Point"}, "properties": {"timestamp": 1552752151.0, "p25": 10}, "type": "Feature"}, {"geometry": {"coordinates": [-74.1380542, 4.6019334], "type": "Point"}, "properties": {"timestamp": 1552752157.0, "p25": 11}, "type": "Feature"}, {"geometry": {"coordinates": [-74.1380542, 4.6019334], "type": "Point"}, "properties": {"timestamp": 1552752162.0, "p25": 11}, "type": "Feature"}, {"geometry": {"coordinates": [-74.1380595, 4.6019483], "type": "Point"}, "properties": {"timestamp": 1552752167.0, "p25": 12}, "type": "Feature"}, {"geometry": {"coordinates": [-74.1380595, 4.6019483], "type": "Point"}, "properties": {"timestamp": 1552752172.0, "p25": 13}, "type": "Feature"}, {"geometry": {"coordinates": [-74.1380457, 4.6019305], "type": "Point"}, "properties": {"timestamp": 1552752177.0, "p25": 14}, "type": "Feature"}, {"geometry": {"coordinates": [-74.1380457, 4.6019305], "type": "Point"}, "properties": {"timestamp": 1552752182.0, "p25": 14}, "type": "Feature"}, {"geometry": {"coordinates": [-74.138038, 4.6019309], "type": "Point"}, "properties": {"timestamp": 1552752187.0, "p25": 14}, "type": "Feature"}, {"geometry": {"coordinates": [-74.138038, 4.6019309], "type": "Point"}, "properties": {"timestamp": 1552752192.0, "p25": 14}, "type": "Feature"}, {"geometry": {"coordinates": [-74.1380305, 4.6019303], "type": "Point"}, "properties": {"timestamp": 1552752198.0, "p25": 12}, "type": "Feature"}, {"geometry": {"coordinates": [-74.1380305, 4.6019303], "type": "Point"}, "properties": {"timestamp": 1552752203.0, "p25": 11}, "type": "Feature"}, {"geometry": {"coordinates": [-74.1380317, 4.6019251], "type": "Point"}, "properties": {"timestamp": 1552752208.0, "p25": 11}, "type": "Feature"}, {"geometry": {"coordinates": [-74.1380317, 4.6019251], "type": "Point"}, "properties": {"timestamp": 1552752213.0, "p25": 12}, "type": "Feature"}, {"geometry": {"coordinates": [-74.138027, 4.6019197], "type": "Point"}, "properties": {"timestamp": 1552752218.0, "p25": 12}, "type": "Feature"}, {"geometry": {"coordinates": [-74.138027, 4.6019197], "type": "Point"}, "properties": {"timestamp": 1552752223.0, "p25": 12}, "type": "Feature"}, {"geometry": {"coordinates": [-74.1380097, 4.6019328], "type": "Point"}, "properties": {"timestamp": 1552752228.0, "p25": 13}, "type": "Feature"}, {"geometry": {"coordinates": [-74.1380097, 4.6019328], "type": "Point"}, "properties": {"timestamp": 1552752233.0, "p25": 14}, "type": "Feature"}, {"geometry": {"coordinates": [-74.1380474, 4.6019411], "type": "Point"}, "properties": {"timestamp": 1552752238.0, "p25": 14}, "type": "Feature"}, {"geometry": {"coordinates": [-74.1380474, 4.6019411], "type": "Point"}, "properties": {"timestamp": 1552752243.0, "p25": 13}, "type": "Feature"}, {"geometry": {"coordinates": [-74.1380579, 4.6019425], "type": "Point"}, "properties": {"timestamp": 1552752249.0, "p25": 13}, "type": "Feature"}, {"geometry": {"coordinates": [-74.1380579, 4.6019425], "type": "Point"}, "properties": {"timestamp": 1552752254.0, "p25": 13}, "type": "Feature"}, {"geometry": {"coordinates": [-74.1380634, 4.6019441], "type": "Point"}, "properties": {"timestamp": 1552752259.0, "p25": 11}, "type": "Feature"}, {"geometry": {"coordinates": [-74.1380634, 4.6019441], "type": "Point"}, "properties": {"timestamp": 1552752264.0, "p25": 11}, "type": "Feature"}, {"geometry": {"coordinates": [-74.1380528, 4.6019433], "type": "Point"}, "properties": {"timestamp": 1552752269.0, "p25": 11}, "type": "Feature"}, {"geometry": {"coordinates": [-74.1380528, 4.6019433], "type": "Point"}, "properties": {"timestamp": 1552752274.0, "p25": 12}, "type": "Feature"}, {"geometry": {"coordinates": [-74.1380498, 4.6019458], "type": "Point"}, "properties": {"timestamp": 1552752279.0, "p25": 11}, "type": "Feature"}, {"geometry": {"coordinates": [-74.1380498, 4.6019458], "type": "Point"}, "properties": {"timestamp": 1552752284.0, "p25": 11}, "type": "Feature"}, {"geometry": {"coordinates": [-74.1380807, 4.6019657], "type": "Point"}, "properties": {"timestamp": 1552752289.0, "p25": 11}, "type": "Feature"}, {"geometry": {"coordinates": [-74.1380807, 4.6019657], "type": "Point"}, "properties": {"timestamp": 1552752295.0, "p25": 12}, "type": "Feature"}, {"geometry": {"coordinates": [-74.1381243, 4.6019635], "type": "Point"}, "properties": {"timestamp": 1552752300.0, "p25": 12}, "type": "Feature"}, {"geometry": {"coordinates": [-74.1381243, 4.6019635], "type": "Point"}, "properties": {"timestamp": 1552752305.0, "p25": 11}, "type": "Feature"}, {"geometry": {"coordinates": [-74.1381341, 4.602049], "type": "Point"}, "properties": {"timestamp": 1552752310.0, "p25": 11}, "type": "Feature"}, {"geometry": {"coordinates": [-74.1381341, 4.602049], "type": "Point"}, "properties": {"timestamp": 1552752315.0, "p25": 14}, "type": "Feature"}, {"geometry": {"coordinates": [-74.1382052, 4.6021669], "type": "Point"}, "properties": {"timestamp": 1552752320.0, "p25": 16}, "type": "Feature"}, {"geometry": {"coordinates": [-74.1382052, 4.6021669], "type": "Point"}, "properties": {"timestamp": 1552752325.0, "p25": 15}, "type": "Feature"}, {"geometry": {"coordinates": [-74.1382579, 4.602215], "type": "Point"}, "properties": {"timestamp": 1552752330.0, "p25": 11}, "type": "Feature"}, {"geometry": {"coordinates": [-74.1382579, 4.602215], "type": "Point"}, "properties": {"timestamp": 1552752335.0, "p25": 9}, "type": "Feature"}, {"geometry": {"coordinates": [-74.1382595, 4.6022314], "type": "Point"}, "properties": {"timestamp": 1552752341.0, "p25": 10}, "type": "Feature"}, {"geometry": {"coordinates": [-74.1382595, 4.6022314], "type": "Point"}, "properties": {"timestamp": 1552752346.0, "p25": 11}, "type": "Feature"}, {"geometry": {"coordinates": [-74.1382032, 4.6021948], "type": "Point"}, "properties": {"timestamp": 1552752351.0, "p25": 12}, "type": "Feature"}, {"geometry": {"coordinates": [-74.1382032, 4.6021948], "type": "Point"}, "properties": {"timestamp": 1552752356.0, "p25": 12}, "type": "Feature"}, {"geometry": {"coordinates": [-74.1381721, 4.6020659], "type": "Point"}, "properties": {"timestamp": 1552752361.0, "p25": 12}, "type": "Feature"}, {"geometry": {"coordinates": [-74.1381721, 4.6020659], "type": "Point"}, "properties": {"timestamp": 1552752366.0, "p25": 15}, "type": "Feature"}, {"geometry": {"coordinates": [-74.1381024, 4.601973], "type": "Point"}, "properties": {"timestamp": 1552752371.0, "p25": 18}, "type": "Feature"}, {"geometry": {"coordinates": [-74.1381024, 4.601973], "type": "Point"}, "properties": {"timestamp": 1552752376.0, "p25": 21}, "type": "Feature"}, {"geometry": {"coordinates": [-74.1381024, 4.601973], "type": "Point"}, "properties": {"timestamp": 1552752381.0, "p25": 22}, "type": "Feature"}, {"geometry": {"coordinates": [-74.1380706, 4.6019159], "type": "Point"}, "properties": {"timestamp": 1552752387.0, "p25": 21}, "type": "Feature"}, {"geometry": {"coordinates": [-74.1380706, 4.6019159], "type": "Point"}, "properties": {"timestamp": 1552752392.0, "p25": 17}, "type": "Feature"}, {"geometry": {"coordinates": [-74.1380574, 4.6019075], "type": "Point"}, "properties": {"timestamp": 1552752397.0, "p25": 13}, "type": "Feature"}, {"geometry": {"coordinates": [-74.1380574, 4.6019075], "type": "Point"}, "properties": {"timestamp": 1552752402.0, "p25": 13}, "type": "Feature"}, {"geometry": {"coordinates": [-74.1380313, 4.601908], "type": "Point"}, "properties": {"timestamp": 1552752407.0, "p25": 13}, "type": "Feature"}, {"geometry": {"coordinates": [-74.1380313, 4.601908], "type": "Point"}, "properties": {"timestamp": 1552752412.0, "p25": 14}, "type": "Feature"}, {"geometry": {"coordinates": [-74.1380414, 4.6018852], "type": "Point"}, "properties": {"timestamp": 1552752417.0, "p25": 15}, "type": "Feature"}, {"geometry": {"coordinates": [-74.1380414, 4.6018852], "type": "Point"}, "properties": {"timestamp": 1552752422.0, "p25": 16}, "type": "Feature"}, {"geometry": {"coordinates": [-74.1381194, 4.6019132], "type": "Point"}, "properties": {"timestamp": 1552752427.0, "p25": 15}, "type": "Feature"}, {"geometry": {"coordinates": [-74.1381194, 4.6019132], "type": "Point"}, "properties": {"timestamp": 1552752432.0, "p25": 12}, "type": "Feature"}, {"geometry": {"coordinates": [-74.1381547, 4.6019425], "type": "Point"}, "properties": {"timestamp": 1552752438.0, "p25": 12}, "type": "Feature"}, {"geometry": {"coordinates": [-74.1381547, 4.6019425], "type": "Point"}, "properties": {"timestamp": 1552752443.0, "p25": 13}, "type": "Feature"}, {"geometry": {"coordinates": [-74.1381844, 4.6019531], "type": "Point"}, "properties": {"timestamp": 1552752448.0, "p25": 14}, "type": "Feature"}, {"geometry": {"coordinates": [-74.1381844, 4.6019531], "type": "Point"}, "properties": {"timestamp": 1552752453.0, "p25": 16}, "type": "Feature"}, {"geometry": {"coordinates": [-74.1381456, 4.6019915], "type": "Point"}, "properties": {"timestamp": 1552752458.0, "p25": 17}, "type": "Feature"}, {"geometry": {"coordinates": [-74.1381456, 4.6019915], "type": "Point"}, "properties": {"timestamp": 1552752463.0, "p25": 18}, "type": "Feature"}, {"geometry": {"coordinates": [-74.138089, 4.6019319], "type": "Point"}, "properties": {"timestamp": 1552752468.0, "p25": 17}, "type": "Feature"}, {"geometry": {"coordinates": [-74.138089, 4.6019319], "type": "Point"}, "properties": {"timestamp": 1552752473.0, "p25": 17}, "type": "Feature"}, {"geometry": {"coordinates": [-74.1380865, 4.601941], "type": "Point"}, "properties": {"timestamp": 1552752479.0, "p25": 18}, "type": "Feature"}, {"geometry": {"coordinates": [-74.1380865, 4.601941], "type": "Point"}, "properties": {"timestamp": 1552752484.0, "p25": 18}, "type": "Feature"}, {"geometry": {"coordinates": [-74.1380512, 4.6019137], "type": "Point"}, "properties": {"timestamp": 1552752489.0, "p25": 17}, "type": "Feature"}, {"geometry": {"coordinates": [-74.1380512, 4.6019137], "type": "Point"}, "properties": {"timestamp": 1552752494.0, "p25": 17}, "type": "Feature"}, {"geometry": {"coordinates": [-74.1380358, 4.6019042], "type": "Point"}, "properties": {"timestamp": 1552752499.0, "p25": 18}, "type": "Feature"}, {"geometry": {"coordinates": [-74.1380358, 4.6019042], "type": "Point"}, "properties": {"timestamp": 1552752504.0, "p25": 18}, "type": "Feature"}, {"geometry": {"coordinates": [-74.1380572, 4.6019307], "type": "Point"}, "properties": {"timestamp": 1552752509.0, "p25": 17}, "type": "Feature"}, {"geometry": {"coordinates": [-74.1380572, 4.6019307], "type": "Point"}, "properties": {"timestamp": 1552752514.0, "p25": 17}, "type": "Feature"}, {"geometry": {"coordinates": [-74.1380599, 4.6019392], "type": "Point"}, "properties": {"timestamp": 1552752520.0, "p25": 17}, "type": "Feature"}, {"geometry": {"coordinates": [-74.1380599, 4.6019392], "type": "Point"}, "properties": {"timestamp": 1552752525.0, "p25": 17}, "type": "Feature"}, {"geometry": {"coordinates": [-74.1381141, 4.6019427], "type": "Point"}, "properties": {"timestamp": 1552752530.0, "p25": 18}, "type": "Feature"}, {"geometry": {"coordinates": [-74.1381141, 4.6019427], "type": "Point"}, "properties": {"timestamp": 1552752535.0, "p25": 19}, "type": "Feature"}, {"geometry": {"coordinates": [-74.1381507, 4.6020354], "type": "Point"}, "properties": {"timestamp": 1552752540.0, "p25": 18}, "type": "Feature"}, {"geometry": {"coordinates": [-74.1381507, 4.6020354], "type": "Point"}, "properties": {"timestamp": 1552752545.0, "p25": 16}, "type": "Feature"}, {"geometry": {"coordinates": [-74.1381507, 4.6020354], "type": "Point"}, "properties": {"timestamp": 1552752550.0, "p25": 15}, "type": "Feature"}, {"geometry": {"coordinates": [-74.138179, 4.602117], "type": "Point"}, "properties": {"timestamp": 1552752555.0, "p25": 14}, "type": "Feature"}, {"geometry": {"coordinates": [-74.138179, 4.602117], "type": "Point"}, "properties": {"timestamp": 1552752560.0, "p25": 14}, "type": "Feature"}, {"geometry": {"coordinates": [-74.1382043, 4.6021387], "type": "Point"}, "properties": {"timestamp": 1552752565.0, "p25": 14}, "type": "Feature"}, {"geometry": {"coordinates": [-74.1382043, 4.6021387], "type": "Point"}, "properties": {"timestamp": 1552752571.0, "p25": 14}, "type": "Feature"}, {"geometry": {"coordinates": [-74.1383004, 4.6023492], "type": "Point"}, "properties": {"timestamp": 1552752576.0, "p25": 13}, "type": "Feature"}, {"geometry": {"coordinates": [-74.1383004, 4.6023492], "type": "Point"}, "properties": {"timestamp": 1552752581.0, "p25": 13}, "type": "Feature"}, {"geometry": {"coordinates": [-74.1383735, 4.6024614], "type": "Point"}, "properties": {"timestamp": 1552752586.0, "p25": 14}, "type": "Feature"}, {"geometry": {"coordinates": [-74.1383735, 4.6024614], "type": "Point"}, "properties": {"timestamp": 1552752591.0, "p25": 15}, "type": "Feature"}, {"geometry": {"coordinates": [-74.1384158, 4.6025387], "type": "Point"}, "properties": {"timestamp": 1552752596.0, "p25": 15}, "type": "Feature"}, {"geometry": {"coordinates": [-74.1384158, 4.6025387], "type": "Point"}, "properties": {"timestamp": 1552752601.0, "p25": 13}, "type": "Feature"}, {"geometry": {"coordinates": [-74.1385555, 4.602667], "type": "Point"}, "properties": {"timestamp": 1552752606.0, "p25": 13}, "type": "Feature"}, {"geometry": {"coordinates": [-74.1385347, 4.6026954], "type": "Point"}, "properties": {"timestamp": 1552752611.0, "p25": 14}, "type": "Feature"}, {"geometry": {"coordinates": [-74.1385347, 4.6026954], "type": "Point"}, "properties": {"timestamp": 1552752617.0, "p25": 15}, "type": "Feature"}, {"geometry": {"coordinates": [-74.1385398, 4.6027303], "type": "Point"}, "properties": {"timestamp": 1552752622.0, "p25": 15}, "type": "Feature"}, {"geometry": {"coordinates": [-74.1385398, 4.6027303], "type": "Point"}, "properties": {"timestamp": 1552752627.0, "p25": 14}, "type": "Feature"}, {"geometry": {"coordinates": [-74.1385995, 4.6028138], "type": "Point"}, "properties": {"timestamp": 1552752632.0, "p25": 14}, "type": "Feature"}, {"geometry": {"coordinates": [-74.1385995, 4.6028138], "type": "Point"}, "properties": {"timestamp": 1552752637.0, "p25": 14}, "type": "Feature"}, {"geometry": {"coordinates": [-74.1386495, 4.6029062], "type": "Point"}, "properties": {"timestamp": 1552752642.0, "p25": 16}, "type": "Feature"}, {"geometry": {"coordinates": [-74.1386495, 4.6029062], "type": "Point"}, "properties": {"timestamp": 1552752647.0, "p25": 18}, "type": "Feature"}, {"geometry": {"coordinates": [-74.1386495, 4.6029062], "type": "Point"}, "properties": {"timestamp": 1552752652.0, "p25": 18}, "type": "Feature"}, {"geometry": {"coordinates": [-74.1387234, 4.6030264], "type": "Point"}, "properties": {"timestamp": 1552752658.0, "p25": 16}, "type": "Feature"}, {"geometry": {"coordinates": [-74.1387234, 4.6030264], "type": "Point"}, "properties": {"timestamp": 1552752663.0, "p25": 13}, "type": "Feature"}, {"geometry": {"coordinates": [-74.1387808, 4.6031597], "type": "Point"}, "properties": {"timestamp": 1552752668.0, "p25": 14}, "type": "Feature"}, {"geometry": {"coordinates": [-74.1387808, 4.6031597], "type": "Point"}, "properties": {"timestamp": 1552752673.0, "p25": 16}, "type": "Feature"}, {"geometry": {"coordinates": [-74.1388134, 4.6031874], "type": "Point"}, "properties": {"timestamp": 1552752678.0, "p25": 16}, "type": "Feature"}, {"geometry": {"coordinates": [-74.1388529, 4.6032202], "type": "Point"}, "properties": {"timestamp": 1552752683.0, "p25": 16}, "type": "Feature"}, {"geometry": {"coordinates": [-74.1388529, 4.6032202], "type": "Point"}, "properties": {"timestamp": 1552752688.0, "p25": 15}, "type": "Feature"}, {"geometry": {"coordinates": [-74.1390083, 4.6033456], "type": "Point"}, "properties": {"timestamp": 1552752693.0, "p25": 14}, "type": "Feature"}, {"geometry": {"coordinates": [-74.1390083, 4.6033456], "type": "Point"}, "properties": {"timestamp": 1552752698.0, "p25": 14}, "type": "Feature"}, {"geometry": {"coordinates": [-74.1393663, 4.6032307], "type": "Point"}, "properties": {"timestamp": 1552752704.0, "p25": 13}, "type": "Feature"}, {"geometry": {"coordinates": [-74.1393663, 4.6032307], "type": "Point"}, "properties": {"timestamp": 1552752709.0, "p25": 12}, "type": "Feature"}, {"geometry": {"coordinates": [-74.1393116, 4.6032174], "type": "Point"}, "properties": {"timestamp": 1552752714.0, "p25": 12}, "type": "Feature"}, {"geometry": {"coordinates": [-74.1393116, 4.6032174], "type": "Point"}, "properties": {"timestamp": 1552752719.0, "p25": 12}, "type": "Feature"}, {"geometry": {"coordinates": [-74.1393565, 4.6031111], "type": "Point"}, "properties": {"timestamp": 1552752724.0, "p25": 13}, "type": "Feature"}, {"geometry": {"coordinates": [-74.1393565, 4.6031111], "type": "Point"}, "properties": {"timestamp": 1552752729.0, "p25": 14}, "type": "Feature"}, {"geometry": {"coordinates": [-74.1392874, 4.6031286], "type": "Point"}, "properties": {"timestamp": 1552752734.0, "p25": 15}, "type": "Feature"}, {"geometry": {"coordinates": [-74.1392874, 4.6031286], "type": "Point"}, "properties": {"timestamp": 1552752739.0, "p25": 14}, "type": "Feature"}, {"geometry": {"coordinates": [-74.1393332, 4.6030752], "type": "Point"}, "properties": {"timestamp": 1552752744.0, "p25": 12}, "type": "Feature"}, {"geometry": {"coordinates": [-74.1393332, 4.6030752], "type": "Point"}, "properties": {"timestamp": 1552752750.0, "p25": 11}, "type": "Feature"}, {"geometry": {"coordinates": [-74.1393728, 4.6030647], "type": "Point"}, "properties": {"timestamp": 1552752755.0, "p25": 11}, "type": "Feature"}, {"geometry": {"coordinates": [-74.1393728, 4.6030647], "type": "Point"}, "properties": {"timestamp": 1552752760.0, "p25": 11}, "type": "Feature"}, {"geometry": {"coordinates": [-74.1394299, 4.6030238], "type": "Point"}, "properties": {"timestamp": 1552752765.0, "p25": 11}, "type": "Feature"}, {"geometry": {"coordinates": [-74.1394299, 4.6030238], "type": "Point"}, "properties": {"timestamp": 1552752770.0, "p25": 11}, "type": "Feature"}, {"geometry": {"coordinates": [-74.1394587, 4.603007], "type": "Point"}, "properties": {"timestamp": 1552752775.0, "p25": 11}, "type": "Feature"}, {"geometry": {"coordinates": [-74.1394587, 4.603007], "type": "Point"}, "properties": {"timestamp": 1552752780.0, "p25": 11}, "type": "Feature"}, {"geometry": {"coordinates": [-74.1395295, 4.6029501], "type": "Point"}, "properties": {"timestamp": 1552752785.0, "p25": 11}, "type": "Feature"}, {"geometry": {"coordinates": [-74.1395295, 4.6029501], "type": "Point"}, "properties": {"timestamp": 1552752790.0, "p25": 12}, "type": "Feature"}, {"geometry": {"coordinates": [-74.1396693, 4.602835], "type": "Point"}, "properties": {"timestamp": 1552752796.0, "p25": 12}, "type": "Feature"}, {"geometry": {"coordinates": [-74.1396693, 4.602835], "type": "Point"}, "properties": {"timestamp": 1552752801.0, "p25": 12}, "type": "Feature"}, {"geometry": {"coordinates": [-74.1396976, 4.6027383], "type": "Point"}, "properties": {"timestamp": 1552752806.0, "p25": 11}, "type": "Feature"}, {"geometry": {"coordinates": [-74.1396976, 4.6027383], "type": "Point"}, "properties": {"timestamp": 1552752811.0, "p25": 11}, "type": "Feature"}, {"geometry": {"coordinates": [-74.1397489, 4.6027785], "type": "Point"}, "properties": {"timestamp": 1552752816.0, "p25": 11}, "type": "Feature"}, {"geometry": {"coordinates": [-74.1397489, 4.6027785], "type": "Point"}, "properties": {"timestamp": 1552752821.0, "p25": 11}, "type": "Feature"}, {"geometry": {"coordinates": [-74.1397762, 4.6028082], "type": "Point"}, "properties": {"timestamp": 1552752826.0, "p25": 12}, "type": "Feature"}, {"geometry": {"coordinates": [-74.1397762, 4.6028082], "type": "Point"}, "properties": {"timestamp": 1552752831.0, "p25": 11}, "type": "Feature"}, {"geometry": {"coordinates": [-74.1399743, 4.602511], "type": "Point"}, "properties": {"timestamp": 1552752836.0, "p25": 11}, "type": "Feature"}, {"geometry": {"coordinates": [-74.1399743, 4.602511], "type": "Point"}, "properties": {"timestamp": 1552752842.0, "p25": 11}, "type": "Feature"}, {"geometry": {"coordinates": [-74.1399787, 4.6024785], "type": "Point"}, "properties": {"timestamp": 1552752847.0, "p25": 11}, "type": "Feature"}, {"geometry": {"coordinates": [-74.1399787, 4.6024785], "type": "Point"}, "properties": {"timestamp": 1552752852.0, "p25": 10}, "type": "Feature"}, {"geometry": {"coordinates": [-74.1398737, 4.6026755], "type": "Point"}, "properties": {"timestamp": 1552752857.0, "p25": 10}, "type": "Feature"}, {"geometry": {"coordinates": [-74.1398737, 4.6026755], "type": "Point"}, "properties": {"timestamp": 1552752862.0, "p25": 10}, "type": "Feature"}, {"geometry": {"coordinates": [-74.1398013, 4.6027294], "type": "Point"}, "properties": {"timestamp": 1552752867.0, "p25": 10}, "type": "Feature"}, {"geometry": {"coordinates": [-74.1398013, 4.6027294], "type": "Point"}, "properties": {"timestamp": 1552752872.0, "p25": 11}, "type": "Feature"}, {"geometry": {"coordinates": [-74.1397385, 4.6025998], "type": "Point"}, "properties": {"timestamp": 1552752877.0, "p25": 11}, "type": "Feature"}, {"geometry": {"coordinates": [-74.1397385, 4.6025998], "type": "Point"}, "properties": {"timestamp": 1552752882.0, "p25": 10}, "type": "Feature"}, {"geometry": {"coordinates": [-74.1397507, 4.6025484], "type": "Point"}, "properties": {"timestamp": 1552752887.0, "p25": 10}, "type": "Feature"}, {"geometry": {"coordinates": [-74.1397507, 4.6025484], "type": "Point"}, "properties": {"timestamp": 1552752893.0, "p25": 9}, "type": "Feature"}, {"geometry": {"coordinates": [-74.1397626, 4.6025758], "type": "Point"}, "properties": {"timestamp": 1552752898.0, "p25": 9}, "type": "Feature"}, {"geometry": {"coordinates": [-74.1397626, 4.6025758], "type": "Point"}, "properties": {"timestamp": 1552752903.0, "p25": 9}, "type": "Feature"}, {"geometry": {"coordinates": [-74.1388602, 4.6028566], "type": "Point"}, "properties": {"timestamp": 1552752908.0, "p25": 10}, "type": "Feature"}, {"geometry": {"coordinates": [-74.1388602, 4.6028566], "type": "Point"}, "properties": {"timestamp": 1552752913.0, "p25": 10}, "type": "Feature"}, {"geometry": {"coordinates": [-74.139813, 4.6026096], "type": "Point"}, "properties": {"timestamp": 1552752918.0, "p25": 10}, "type": "Feature"}, {"geometry": {"coordinates": [-74.139813, 4.6026096], "type": "Point"}, "properties": {"timestamp": 1552752923.0, "p25": 11}, "type": "Feature"}, {"geometry": {"coordinates": [-74.1398143, 4.6026179], "type": "Point"}, "properties": {"timestamp": 1552752928.0, "p25": 10}, "type": "Feature"}, {"geometry": {"coordinates": [-74.1398143, 4.6026179], "type": "Point"}, "properties": {"timestamp": 1552752934.0, "p25": 10}, "type": "Feature"}, {"geometry": {"coordinates": [-74.1398208, 4.6025921], "type": "Point"}, "properties": {"timestamp": 1552752939.0, "p25": 10}, "type": "Feature"}, {"geometry": {"coordinates": [-74.1398208, 4.6025921], "type": "Point"}, "properties": {"timestamp": 1552752944.0, "p25": 11}, "type": "Feature"}, {"geometry": {"coordinates": [-74.1398128, 4.602604], "type": "Point"}, "properties": {"timestamp": 1552752949.0, "p25": 12}, "type": "Feature"}, {"geometry": {"coordinates": [-74.1398128, 4.602604], "type": "Point"}, "properties": {"timestamp": 1552752954.0, "p25": 14}, "type": "Feature"}, {"geometry": {"coordinates": [-74.1398134, 4.602605], "type": "Point"}, "properties": {"timestamp": 1552752959.0, "p25": 13}, "type": "Feature"}, {"geometry": {"coordinates": [-74.1398134, 4.602605], "type": "Point"}, "properties": {"timestamp": 1552752964.0, "p25": 12}, "type": "Feature"}, {"geometry": {"coordinates": [-74.1398463, 4.6025157], "type": "Point"}, "properties": {"timestamp": 1552752969.0, "p25": 12}, "type": "Feature"}, {"geometry": {"coordinates": [-74.1398463, 4.6025157], "type": "Point"}, "properties": {"timestamp": 1552752974.0, "p25": 12}, "type": "Feature"}, {"geometry": {"coordinates": [-74.139903, 4.6024579], "type": "Point"}, "properties": {"timestamp": 1552752980.0, "p25": 12}, "type": "Feature"}, {"geometry": {"coordinates": [-74.139903, 4.6024579], "type": "Point"}, "properties": {"timestamp": 1552752985.0, "p25": 13}, "type": "Feature"}, {"geometry": {"coordinates": [-74.1398897, 4.6024865], "type": "Point"}, "properties": {"timestamp": 1552752990.0, "p25": 12}, "type": "Feature"}, {"geometry": {"coordinates": [-74.1398897, 4.6024865], "type": "Point"}, "properties": {"timestamp": 1552752995.0, "p25": 12}, "type": "Feature"}, {"geometry": {"coordinates": [-74.1398731, 4.6025192], "type": "Point"}, "properties": {"timestamp": 1552753000.0, "p25": 12}, "type": "Feature"}, {"geometry": {"coordinates": [-74.1398731, 4.6025192], "type": "Point"}, "properties": {"timestamp": 1552753005.0, "p25": 14}, "type": "Feature"}, {"geometry": {"coordinates": [-74.1399155, 4.6025127], "type": "Point"}, "properties": {"timestamp": 1552753010.0, "p25": 14}, "type": "Feature"}, {"geometry": {"coordinates": [-74.1399155, 4.6025127], "type": "Point"}, "properties": {"timestamp": 1552753015.0, "p25": 13}, "type": "Feature"}, {"geometry": {"coordinates": [-74.1398915, 4.6025359], "type": "Point"}, "properties": {"timestamp": 1552753020.0, "p25": 12}, "type": "Feature"}, {"geometry": {"coordinates": [-74.1398915, 4.6025359], "type": "Point"}, "properties": {"timestamp": 1552753025.0, "p25": 12}, "type": "Feature"}, {"geometry": {"coordinates": [-74.1399072, 4.6025325], "type": "Point"}, "properties": {"timestamp": 1552753031.0, "p25": 13}, "type": "Feature"}, {"geometry": {"coordinates": [-74.1399072, 4.6025325], "type": "Point"}, "properties": {"timestamp": 1552753036.0, "p25": 13}, "type": "Feature"}, {"geometry": {"coordinates": [-74.1399475, 4.6024259], "type": "Point"}, "properties": {"timestamp": 1552753041.0, "p25": 12}, "type": "Feature"}, {"geometry": {"coordinates": [-74.1399475, 4.6024259], "type": "Point"}, "properties": {"timestamp": 1552753046.0, "p25": 13}, "type": "Feature"}, {"geometry": {"coordinates": [-74.140014, 4.6024039], "type": "Point"}, "properties": {"timestamp": 1552753051.0, "p25": 14}, "type": "Feature"}, {"geometry": {"coordinates": [-74.140014, 4.6024039], "type": "Point"}, "properties": {"timestamp": 1552753056.0, "p25": 14}, "type": "Feature"}, {"geometry": {"coordinates": [-74.1400029, 4.6024289], "type": "Point"}, "properties": {"timestamp": 1552753061.0, "p25": 13}, "type": "Feature"}, {"geometry": {"coordinates": [-74.1400029, 4.6024289], "type": "Point"}, "properties": {"timestamp": 1552753066.0, "p25": 12}, "type": "Feature"}, {"geometry": {"coordinates": [-74.1399475, 4.6024799], "type": "Point"}, "properties": {"timestamp": 1552753071.0, "p25": 14}, "type": "Feature"}, {"geometry": {"coordinates": [-74.1399475, 4.6024799], "type": "Point"}, "properties": {"timestamp": 1552753077.0, "p25": 18}, "type": "Feature"}, {"geometry": {"coordinates": [-74.1399393, 4.6024559], "type": "Point"}, "properties": {"timestamp": 1552753082.0, "p25": 21}, "type": "Feature"}, {"geometry": {"coordinates": [-74.1399393, 4.6024559], "type": "Point"}, "properties": {"timestamp": 1552753087.0, "p25": 22}, "type": "Feature"}, {"geometry": {"coordinates": [-74.1400187, 4.602477], "type": "Point"}, "properties": {"timestamp": 1552753092.0, "p25": 23}, "type": "Feature"}, {"geometry": {"coordinates": [-74.1400187, 4.602477], "type": "Point"}, "properties": {"timestamp": 1552753097.0, "p25": 25}, "type": "Feature"}, {"geometry": {"coordinates": [-74.13995, 4.6025175], "type": "Point"}, "properties": {"timestamp": 1552753102.0, "p25": 27}, "type": "Feature"}, {"geometry": {"coordinates": [-74.13995, 4.6025175], "type": "Point"}, "properties": {"timestamp": 1552753107.0, "p25": 24}, "type": "Feature"}, {"geometry": {"coordinates": [-74.1399737, 4.6024603], "type": "Point"}, "properties": {"timestamp": 1552753112.0, "p25": 19}, "type": "Feature"}, {"geometry": {"coordinates": [-74.1399737, 4.6024603], "type": "Point"}, "properties": {"timestamp": 1552753117.0, "p25": 15}, "type": "Feature"}, {"geometry": {"coordinates": [-74.1398987, 4.6025351], "type": "Point"}, "properties": {"timestamp": 1552753123.0, "p25": 15}, "type": "Feature"}, {"geometry": {"coordinates": [-74.1398987, 4.6025351], "type": "Point"}, "properties": {"timestamp": 1552753128.0, "p25": 15}, "type": "Feature"}, {"geometry": {"coordinates": [-74.1398458, 4.6026732], "type": "Point"}, "properties": {"timestamp": 1552753133.0, "p25": 15}, "type": "Feature"}, {"geometry": {"coordinates": [-74.1398458, 4.6026732], "type": "Point"}, "properties": {"timestamp": 1552753138.0, "p25": 15}, "type": "Feature"}, {"geometry": {"coordinates": [-74.1397987, 4.6027961], "type": "Point"}, "properties": {"timestamp": 1552753143.0, "p25": 17}, "type": "Feature"}, {"geometry": {"coordinates": [-74.1397987, 4.6027961], "type": "Point"}, "properties": {"timestamp": 1552753148.0, "p25": 19}, "type": "Feature"}, {"geometry": {"coordinates": [-74.1397741, 4.602759], "type": "Point"}, "properties": {"timestamp": 1552753153.0, "p25": 17}, "type": "Feature"}, {"geometry": {"coordinates": [-74.1397741, 4.602759], "type": "Point"}, "properties": {"timestamp": 1552753158.0, "p25": 13}, "type": "Feature"}, {"geometry": {"coordinates": [-74.1397905, 4.6026539], "type": "Point"}, "properties": {"timestamp": 1552753163.0, "p25": 11}, "type": "Feature"}, {"geometry": {"coordinates": [-74.1397905, 4.6026539], "type": "Point"}, "properties": {"timestamp": 1552753169.0, "p25": 11}, "type": "Feature"}, {"geometry": {"coordinates": [-74.1397446, 4.6025881], "type": "Point"}, "properties": {"timestamp": 1552753174.0, "p25": 13}, "type": "Feature"}, {"geometry": {"coordinates": [-74.1397446, 4.6025881], "type": "Point"}, "properties": {"timestamp": 1552753179.0, "p25": 14}, "type": "Feature"}, {"geometry": {"coordinates": [-74.1397198, 4.602511], "type": "Point"}, "properties": {"timestamp": 1552753184.0, "p25": 15}, "type": "Feature"}, {"geometry": {"coordinates": [-74.1397198, 4.602511], "type": "Point"}, "properties": {"timestamp": 1552753189.0, "p25": 14}, "type": "Feature"}, {"geometry": {"coordinates": [-74.1397343, 4.6025138], "type": "Point"}, "properties": {"timestamp": 1552753194.0, "p25": 12}, "type": "Feature"}, {"geometry": {"coordinates": [-74.1397343, 4.6025138], "type": "Point"}, "properties": {"timestamp": 1552753199.0, "p25": 12}, "type": "Feature"}, {"geometry": {"coordinates": [-74.1397519, 4.6025813], "type": "Point"}, "properties": {"timestamp": 1552753205.0, "p25": 12}, "type": "Feature"}, {"geometry": {"coordinates": [-74.1397519, 4.6025813], "type": "Point"}, "properties": {"timestamp": 1552753210.0, "p25": 12}, "type": "Feature"}, {"geometry": {"coordinates": [-74.1397595, 4.6025967], "type": "Point"}, "properties": {"timestamp": 1552753215.0, "p25": 12}, "type": "Feature"}, {"geometry": {"coordinates": [-74.1397595, 4.6025967], "type": "Point"}, "properties": {"timestamp": 1552753220.0, "p25": 12}, "type": "Feature"}, {"geometry": {"coordinates": [-74.1397572, 4.6026393], "type": "Point"}, "properties": {"timestamp": 1552753225.0, "p25": 12}, "type": "Feature"}, {"geometry": {"coordinates": [-74.1397572, 4.6026393], "type": "Point"}, "properties": {"timestamp": 1552753230.0, "p25": 12}, "type": "Feature"}, {"geometry": {"coordinates": [-74.1397375, 4.6026396], "type": "Point"}, "properties": {"timestamp": 1552753235.0, "p25": 13}, "type": "Feature"}, {"geometry": {"coordinates": [-74.1397375, 4.6026396], "type": "Point"}, "properties": {"timestamp": 1552753240.0, "p25": 12}, "type": "Feature"}, {"geometry": {"coordinates": [-74.1397131, 4.6026508], "type": "Point"}, "properties": {"timestamp": 1552753245.0, "p25": 12}, "type": "Feature"}, {"geometry": {"coordinates": [-74.1397131, 4.6026508], "type": "Point"}, "properties": {"timestamp": 1552753250.0, "p25": 13}, "type": "Feature"}, {"geometry": {"coordinates": [-74.1397729, 4.6026032], "type": "Point"}, "properties": {"timestamp": 1552753255.0, "p25": 13}, "type": "Feature"}, {"geometry": {"coordinates": [-74.1397729, 4.6026032], "type": "Point"}, "properties": {"timestamp": 1552753261.0, "p25": 12}, "type": "Feature"}, {"geometry": {"coordinates": [-74.1398387, 4.6025891], "type": "Point"}, "properties": {"timestamp": 1552753266.0, "p25": 11}, "type": "Feature"}, {"geometry": {"coordinates": [-74.1398387, 4.6025891], "type": "Point"}, "properties": {"timestamp": 1552753271.0, "p25": 11}, "type": "Feature"}, {"geometry": {"coordinates": [-74.1398078, 4.6026022], "type": "Point"}, "properties": {"timestamp": 1552753276.0, "p25": 11}, "type": "Feature"}, {"geometry": {"coordinates": [-74.1398078, 4.6026022], "type": "Point"}, "properties": {"timestamp": 1552753281.0, "p25": 11}, "type": "Feature"}, {"geometry": {"coordinates": [-74.1398297, 4.6025781], "type": "Point"}, "properties": {"timestamp": 1552753286.0, "p25": 11}, "type": "Feature"}, {"geometry": {"coordinates": [-74.1398297, 4.6025781], "type": "Point"}, "properties": {"timestamp": 1552753291.0, "p25": 13}, "type": "Feature"}, {"geometry": {"coordinates": [-74.1398534, 4.6025428], "type": "Point"}, "properties": {"timestamp": 1552753296.0, "p25": 14}, "type": "Feature"}, {"geometry": {"coordinates": [-74.1398534, 4.6025428], "type": "Point"}, "properties": {"timestamp": 1552753301.0, "p25": 14}, "type": "Feature"}, {"geometry": {"coordinates": [-74.139823, 4.6025714], "type": "Point"}, "properties": {"timestamp": 1552753307.0, "p25": 13}, "type": "Feature"}, {"geometry": {"coordinates": [-74.139823, 4.6025714], "type": "Point"}, "properties": {"timestamp": 1552753312.0, "p25": 14}, "type": "Feature"}, {"geometry": {"coordinates": [-74.1398683, 4.6025488], "type": "Point"}, "properties": {"timestamp": 1552753317.0, "p25": 12}, "type": "Feature"}, {"geometry": {"coordinates": [-74.1398683, 4.6025488], "type": "Point"}, "properties": {"timestamp": 1552753322.0, "p25": 10}, "type": "Feature"}, {"geometry": {"coordinates": [-74.1399414, 4.6025157], "type": "Point"}, "properties": {"timestamp": 1552753327.0, "p25": 10}, "type": "Feature"}, {"geometry": {"coordinates": [-74.1399414, 4.6025157], "type": "Point"}, "properties": {"timestamp": 1552753332.0, "p25": 11}, "type": "Feature"}, {"geometry": {"coordinates": [-74.1399954, 4.6025105], "type": "Point"}, "properties": {"timestamp": 1552753337.0, "p25": 16}, "type": "Feature"}, {"geometry": {"coordinates": [-74.1399954, 4.6025105], "type": "Point"}, "properties": {"timestamp": 1552753342.0, "p25": 25}, "type": "Feature"}, {"geometry": {"coordinates": [-74.139855, 4.6026541], "type": "Point"}, "properties": {"timestamp": 1552753347.0, "p25": 30}, "type": "Feature"}, {"geometry": {"coordinates": [-74.139855, 4.6026541], "type": "Point"}, "properties": {"timestamp": 1552753353.0, "p25": 28}, "type": "Feature"}, {"geometry": {"coordinates": [-74.1396435, 4.6028332], "type": "Point"}, "properties": {"timestamp": 1552753358.0, "p25": 24}, "type": "Feature"}, {"geometry": {"coordinates": [-74.1396435, 4.6028332], "type": "Point"}, "properties": {"timestamp": 1552753363.0, "p25": 21}, "type": "Feature"}, {"geometry": {"coordinates": [-74.139602, 4.6029768], "type": "Point"}, "properties": {"timestamp": 1552753368.0, "p25": 20}, "type": "Feature"}, {"geometry": {"coordinates": [-74.139602, 4.6029768], "type": "Point"}, "properties": {"timestamp": 1552753373.0, "p25": 20}, "type": "Feature"}, {"geometry": {"coordinates": [-74.1388547, 4.6029681], "type": "Point"}, "properties": {"timestamp": 1552753378.0, "p25": 22}, "type": "Feature"}, {"geometry": {"coordinates": [-74.1388547, 4.6029681], "type": "Point"}, "properties": {"timestamp": 1552753383.0, "p25": 23}, "type": "Feature"}, {"geometry": {"coordinates": [-74.1382356, 4.6022366], "type": "Point"}, "properties": {"timestamp": 1552753388.0, "p25": 22}, "type": "Feature"}, {"geometry": {"coordinates": [-74.1382356, 4.6022366], "type": "Point"}, "properties": {"timestamp": 1552753394.0, "p25": 20}, "type": "Feature"}, {"geometry": {"coordinates": [-74.1380446, 4.6019016], "type": "Point"}, "properties": {"timestamp": 1552753399.0, "p25": 21}, "type": "Feature"}, {"geometry": {"coordinates": [-74.1380446, 4.6019016], "type": "Point"}, "properties": {"timestamp": 1552753404.0, "p25": 26}, "type": "Feature"}, {"geometry": {"coordinates": [-74.1380215, 4.601861], "type": "Point"}, "properties": {"timestamp": 1552753409.0, "p25": 26}, "type": "Feature"}, {"geometry": {"coordinates": [-74.138019, 4.6018568], "type": "Point"}, "properties": {"timestamp": 1552753414.0, "p25": 23}, "type": "Feature"}]